{
  "1556150400000": {
    "Biomass": 173.0,
    "Fossil Brown coal/Lignite": 0.0,
    "Fossil Coal-derived gas": 0.0,
    "Fossil Gas": 3963.0,
    "Fossil Hard coal": 582.0,
    "Fossil Oil": 197.0,
    "Fossil Oil shale": 0.0,
    "Fossil Peat": 0.0,
    "Geothermal": 0.0,
    "Hydro Pumped Storage": 2394.0,
    "Hydro Run-of-river and poundage": 1138.0,
    "Hydro Water Reservoir": 448.0,
    "Marine": 0.0,
    "Nuclear": 6983.0,
    "Other": 11.0,
    "Other renewable": 102.0,
    "Solar": 131.0,
    "Waste": 255.0,
    "Wind Offshore": 0.0,
    "Wind Onshore": 12944.0
  },
  "1556154000000": {
    "Biomass": 171.0,
    "Fossil Brown coal/Lignite": 0.0,
    "Fossil Coal-derived gas": 0.0,
    "Fossil Gas": 3997.0,
    "Fossil Hard coal": 553.0,
    "Fossil Oil": 194.0,
    "Fossil Oil shale": 0.0,
    "Fossil Peat": 0.0,
    "Geothermal": 0.0,
    "Hydro Pumped Storage": 2681.0,
    "Hydro Run-of-river and poundage": 1160.0,
    "Hydro Water Reservoir": 469.0,
    "Marine": 0.0,
    "Nuclear": 6984.0,
    "Other": 12.0,
    "Other renewable": 103.0,
    "Solar": 131.0,
    "Waste": 259.0,
    "Wind Offshore": 0.0,
    "Wind Onshore": 11138.0
  },
  "1556157600000": {
    "Biomass": 174.0,
    "Fossil Brown coal/Lignite": 0.0,
    "Fossil Coal-derived gas": 0.0,
    "Fossil Gas": 4001.0,
    "Fossil Hard coal": 565.0,
    "Fossil Oil": 194.0,
    "Fossil Oil shale": 0.0,
    "Fossil Peat": 0.0,
    "Geothermal": 0.0,
    "Hydro Pumped Storage": 2719.0,
    "Hydro Run-of-river and poundage": 1163.0,
    "Hydro Water Reservoir": 452.0,
    "Marine": 0.0,
    "Nuclear": 6982.0,
    "Other": 13.0,
    "Other renewable": 105.0,
    "Solar": 133.0,
    "Waste": 255.0,
    "Wind Offshore": 0.0,
    "Wind Onshore": 10090.0
  },
  "1556161200000": {
    "Biomass": 175.0,
    "Fossil Brown coal/Lignite": 0.0,
    "Fossil Coal-derived gas": 0.0,
    "Fossil Gas": 4391.0,
    "Fossil Hard coal": 705.0,
    "Fossil Oil": 188.0,
    "Fossil Oil shale": 0.0,
    "Fossil Peat": 0.0,
    "Geothermal": 0.0,
    "Hydro Pumped Storage": 2707.0,
    "Hydro Run-of-river and poundage": 1206.0,
    "Hydro Water Reservoir": 524.0,
    "Marine": 0.0,
    "Nuclear": 6982.0,
    "Other": 13.0,
    "Other renewable": 103.0,
    "Solar": 105.0,
    "Waste": 256.0,
    "Wind Offshore": 0.0,
    "Wind Onshore": 10605.0
  },
  "1556164800000": {
    "Biomass": 174.0,
    "Fossil Brown coal/Lignite": 0.0,
    "Fossil Coal-derived gas": 0.0,
    "Fossil Gas": 4431.0,
    "Fossil Hard coal": 690.0,
    "Fossil Oil": 190.0,
    "Fossil Oil shale": 0.0,
    "Fossil Peat": 0.0,
    "Geothermal": 0.0,
    "Hydro Pumped Storage": 2345.0,
    "Hydro Run-of-river and poundage": 1236.0,
    "Hydro Water Reservoir": 992.0,
    "Marine": 0.0,
    "Nuclear": 6979.0,
    "Other": 14.0,
    "Other renewable": 106.0,
    "Solar": 68.0,
    "Waste": 256.0,
    "Wind Offshore": 0.0,
    "Wind Onshore": 11145.0
  },
  "1556168400000": {
    "Biomass": 173.0,
    "Fossil Brown coal/Lignite": 0.0,
    "Fossil Coal-derived gas": 0.0,
    "Fossil Gas": 4621.0,
    "Fossil Hard coal": 736.0,
    "Fossil Oil": 214.0,
    "Fossil Oil shale": 0.0,
    "Fossil Peat": 0.0,
    "Geothermal": 0.0,
    "Hydro Pumped Storage": 975.0,
    "Hydro Run-of-river and poundage": 1254.0,
    "Hydro Water Reservoir": 1711.0,
    "Marine": 0.0,
    "Nuclear": 6980.0,
    "Other": 14.0,
    "Other renewable": 109.0,
    "Solar": 49.0,
    "Waste": 254.0,
    "Wind Offshore": 0.0,
    "Wind Onshore": 10170.0
  },
  "1556172000000": {
    "Biomass": 175.0,
    "Fossil Brown coal/Lignite": 0.0,
    "Fossil Coal-derived gas": 0.0,
    "Fossil Gas": 4578.0,
    "Fossil Hard coal": 757.0,
    "Fossil Oil": 231.0,
    "Fossil Oil shale": 0.0,
    "Fossil Peat": 0.0,
    "Geothermal": 0.0,
    "Hydro Pumped Storage": 238.0,
    "Hydro Run-of-river and poundage": 1272.0,
    "Hydro Water Reservoir": 2606.0,
    "Marine": 0.0,
    "Nuclear": 6983.0,
    "Other": 15.0,
    "Other renewable": 109.0,
    "Solar": 266.0,
    "Waste": 255.0,
    "Wind Offshore": 0.0,
    "Wind Onshore": 9677.0
  },
  "1556175600000": {
    "Biomass": 165.0,
    "Fossil Brown coal/Lignite": 0.0,
    "Fossil Coal-derived gas": 0.0,
    "Fossil Gas": 4534.0,
    "Fossil Hard coal": 744.0,
    "Fossil Oil": 232.0,
    "Fossil Oil shale": 0.0,
    "Fossil Peat": 0.0,
    "Geothermal": 0.0,
    "Hydro Pumped Storage": 147.0,
    "Hydro Run-of-river and poundage": 1279.0,
    "Hydro Water Reservoir": 2894.0,
    "Marine": 0.0,
    "Nuclear": 6986.0,
    "Other": 15.0,
    "Other renewable": 110.0,
    "Solar": 718.0,
    "Waste": 260.0,
    "Wind Offshore": 0.0,
    "Wind Onshore": 9645.0
  },
  "1556179200000": {
    "Biomass": 165.0,
    "Fossil Brown coal/Lignite": 0.0,
    "Fossil Coal-derived gas": 0.0,
    "Fossil Gas": 4632.0,
    "Fossil Hard coal": 704.0,
    "Fossil Oil": 229.0,
    "Fossil Oil shale": 0.0,
    "Fossil Peat": 0.0,
    "Geothermal": 0.0,
    "Hydro Pumped Storage": 147.0,
    "Hydro Run-of-river and poundage": 1304.0,
    "Hydro Water Reservoir": 2565.0,
    "Marine": 0.0,
    "Nuclear": 6988.0,
    "Other": 15.0,
    "Other renewable": 110.0,
    "Solar": 1182.0,
    "Waste": 260.0,
    "Wind Offshore": 0.0,
    "Wind Onshore": 10241.0
  },
  "1556182800000": {
    "Biomass": 167.0,
    "Fossil Brown coal/Lignite": 0.0,
    "Fossil Coal-derived gas": 0.0,
    "Fossil Gas": 4614.0,
    "Fossil Hard coal": 694.0,
    "Fossil Oil": 225.0,
    "Fossil Oil shale": 0.0,
    "Fossil Peat": 0.0,
    "Geothermal": 0.0,
    "Hydro Pumped Storage": 147.0,
    "Hydro Run-of-river and poundage": 1329.0,
    "Hydro Water Reservoir": 2256.0,
    "Marine": 0.0,
    "Nuclear": 6990.0,
    "Other": 14.0,
    "Other renewable": 109.0,
    "Solar": 1603.0,
    "Waste": 250.0,
    "Wind Offshore": 0.0,
    "Wind Onshore": 11057.0
  },
  "1556186400000": {
    "Biomass": 165.0,
    "Fossil Brown coal/Lignite": 0.0,
    "Fossil Coal-derived gas": 0.0,
    "Fossil Gas": 4804.0,
    "Fossil Hard coal": 699.0,
    "Fossil Oil": 230.0,
    "Fossil Oil shale": 0.0,
    "Fossil Peat": 0.0,
    "Geothermal": 0.0,
    "Hydro Pumped Storage": 178.0,
    "Hydro Run-of-river and poundage": 1336.0,
    "Hydro Water Reservoir": 1569.0,
    "Marine": 0.0,
    "Nuclear": 6988.0,
    "Other": 19.0,
    "Other renewable": 111.0,
    "Solar": 1886.0,
    "Waste": 240.0,
    "Wind Offshore": 0.0,
    "Wind Onshore": 12055.0
  },
  "1556190000000": {
    "Biomass": 168.0,
    "Fossil Brown coal/Lignite": 0.0,
    "Fossil Coal-derived gas": 0.0,
    "Fossil Gas": 4722.0,
    "Fossil Hard coal": 686.0,
    "Fossil Oil": 229.0,
    "Fossil Oil shale": 0.0,
    "Fossil Peat": 0.0,
    "Geothermal": 0.0,
    "Hydro Pumped Storage": 691.0,
    "Hydro Run-of-river and poundage": 1336.0,
    "Hydro Water Reservoir": 1455.0,
    "Marine": 0.0,
    "Nuclear": 6984.0,
    "Other": 22.0,
    "Other renewable": 110.0,
    "Solar": 2042.0,
    "Waste": 261.0,
    "Wind Offshore": 0.0,
    "Wind Onshore": 12595.0
  },
  "1556193600000": {
    "Biomass": 167.0,
    "Fossil Brown coal/Lignite": 0.0,
    "Fossil Coal-derived gas": 0.0,
    "Fossil Gas": 4560.0,
    "Fossil Hard coal": 664.0,
    "Fossil Oil": 218.0,
    "Fossil Oil shale": 0.0,
    "Fossil Peat": 0.0,
    "Geothermal": 0.0,
    "Hydro Pumped Storage": 775.0,
    "Hydro Run-of-river and poundage": 1340.0,
    "Hydro Water Reservoir": 1181.0,
    "Marine": 0.0,
    "Nuclear": 6984.0,
    "Other": 14.0,
    "Other renewable": 111.0,
    "Solar": 2220.0,
    "Waste": 261.0,
    "Wind Offshore": 0.0,
    "Wind Onshore": 13120.0
  },
  "1556197200000": {
    "Biomass": 162.0,
    "Fossil Brown coal/Lignite": 0.0,
    "Fossil Coal-derived gas": 0.0,
    "Fossil Gas": 4425.0,
    "Fossil Hard coal": 714.0,
    "Fossil Oil": 218.0,
    "Fossil Oil shale": 0.0,
    "Fossil Peat": 0.0,
    "Geothermal": 0.0,
    "Hydro Pumped Storage": 1059.0,
    "Hydro Run-of-river and poundage": 1337.0,
    "Hydro Water Reservoir": 983.0,
    "Marine": 0.0,
    "Nuclear": 6983.0,
    "Other": 14.0,
    "Other renewable": 113.0,
    "Solar": 2324.0,
    "Waste": 257.0,
    "Wind Offshore": 0.0,
    "Wind Onshore": 13446.0
  },
  "1556200800000": {
    "Biomass": 158.0,
    "Fossil Brown coal/Lignite": 0.0,
    "Fossil Coal-derived gas": 0.0,
    "Fossil Gas": 4315.0,
    "Fossil Hard coal": 684.0,
    "Fossil Oil": 218.0,
    "Fossil Oil shale": 0.0,
    "Fossil Peat": 0.0,
    "Geothermal": 0.0,
    "Hydro Pumped Storage": 1268.0,
    "Hydro Run-of-river and poundage": 1326.0,
    "Hydro Water Reservoir": 944.0,
    "Marine": 0.0,
    "Nuclear": 6980.0,
    "Other": 14.0,
    "Other renewable": 114.0,
    "Solar": 2205.0,
    "Waste": 258.0,
    "Wind Offshore": 0.0,
    "Wind Onshore": 14117.0
  },
  "1556204400000": {
    "Biomass": 161.0,
    "Fossil Brown coal/Lignite": 0.0,
    "Fossil Coal-derived gas": 0.0,
    "Fossil Gas": 4027.0,
    "Fossil Hard coal": 695.0,
    "Fossil Oil": 209.0,
    "Fossil Oil shale": 0.0,
    "Fossil Peat": 0.0,
    "Geothermal": 0.0,
    "Hydro Pumped Storage": 1273.0,
    "Hydro Run-of-river and poundage": 1323.0,
    "Hydro Water Reservoir": 849.0,
    "Marine": 0.0,
    "Nuclear": 6982.0,
    "Other": 13.0,
    "Other renewable": 115.0,
    "Solar": 2096.0,
    "Waste": 258.0,
    "Wind Offshore": 0.0,
    "Wind Onshore": 14260.0
  },
  "1556208000000": {
    "Biomass": 168.0,
    "Fossil Brown coal/Lignite": 0.0,
    "Fossil Coal-derived gas": 0.0,
    "Fossil Gas": 4053.0,
    "Fossil Hard coal": 712.0,
    "Fossil Oil": 220.0,
    "Fossil Oil shale": 0.0,
    "Fossil Peat": 0.0,
    "Geothermal": 0.0,
    "Hydro Pumped Storage": 1262.0,
    "Hydro Run-of-river and poundage": 1348.0,
    "Hydro Water Reservoir": 1123.0,
    "Marine": 0.0,
    "Nuclear": 6980.0,
    "Other": 13.0,
    "Other renewable": 115.0,
    "Solar": 1881.0,
    "Waste": 259.0,
    "Wind Offshore": 0.0,
    "Wind Onshore": 14001.0
  },
  "1556211600000": {
    "Biomass": 174.0,
    "Fossil Brown coal/Lignite": 0.0,
    "Fossil Coal-derived gas": 0.0,
    "Fossil Gas": 4353.0,
    "Fossil Hard coal": 707.0,
    "Fossil Oil": 238.0,
    "Fossil Oil shale": 0.0,
    "Fossil Peat": 0.0,
    "Geothermal": 0.0,
    "Hydro Pumped Storage": 527.0,
    "Hydro Run-of-river and poundage": 1380.0,
    "Hydro Water Reservoir": 1463.0,
    "Marine": 0.0,
    "Nuclear": 6978.0,
    "Other": 14.0,
    "Other renewable": 114.0,
    "Solar": 1426.0,
    "Waste": 256.0,
    "Wind Offshore": 0.0,
    "Wind Onshore": 13594.0
  },
  "1556215200000": {
    "Biomass": 177.0,
    "Fossil Brown coal/Lignite": 0.0,
    "Fossil Coal-derived gas": 0.0,
    "Fossil Gas": 3956.0,
    "Fossil Hard coal": 667.0,
    "Fossil Oil": 248.0,
    "Fossil Oil shale": 0.0,
    "Fossil Peat": 0.0,
    "Geothermal": 0.0,
    "Hydro Pumped Storage": 230.0,
    "Hydro Run-of-river and poundage": 1400.0,
    "Hydro Water Reservoir": 1850.0,
    "Marine": 0.0,
    "Nuclear": 6985.0,
    "Other": 15.0,
    "Other renewable": 107.0,
    "Solar": 584.0,
    "Waste": 262.0,
    "Wind Offshore": 0.0,
    "Wind Onshore": 13199.0
  },
  "1556218800000": {
    "Biomass": 178.0,
    "Fossil Brown coal/Lignite": 0.0,
    "Fossil Coal-derived gas": 0.0,
    "Fossil Gas": 4527.0,
    "Fossil Hard coal": 683.0,
    "Fossil Oil": 248.0,
    "Fossil Oil shale": 0.0,
    "Fossil Peat": 0.0,
    "Geothermal": 0.0,
    "Hydro Pumped Storage": 54.0,
    "Hydro Run-of-river and poundage": 1423.0,
    "Hydro Water Reservoir": 2563.0,
    "Marine": 0.0,
    "Nuclear": 6991.0,
    "Other": 14.0,
    "Other renewable": 109.0,
    "Solar": 255.0,
    "Waste": 268.0,
    "Wind Offshore": 0.0,
    "Wind Onshore": 12246.0
  },
  "1556222400000": {
    "Biomass": 177.0,
    "Fossil Brown coal/Lignite": 0.0,
    "Fossil Coal-derived gas": 0.0,
    "Fossil Gas": 4498.0,
    "Fossil Hard coal": 731.0,
    "Fossil Oil": 253.0,
    "Fossil Oil shale": 0.0,
    "Fossil Peat": 0.0,
    "Geothermal": 0.0,
    "Hydro Pumped Storage": 2.0,
    "Hydro Run-of-river and poundage": 1405.0,
    "Hydro Water Reservoir": 2169.0,
    "Marine": 0.0,
    "Nuclear": 6991.0,
    "Other": 14.0,
    "Other renewable": 109.0,
    "Solar": 173.0,
    "Waste": 266.0,
    "Wind Offshore": 0.0,
    "Wind Onshore": 12215.0
  },
  "1556226000000": {
    "Biomass": 177.0,
    "Fossil Brown coal/Lignite": 0.0,
    "Fossil Coal-derived gas": 0.0,
    "Fossil Gas": 4391.0,
    "Fossil Hard coal": 710.0,
    "Fossil Oil": 247.0,
    "Fossil Oil shale": 0.0,
    "Fossil Peat": 0.0,
    "Geothermal": 0.0,
    "Hydro Pumped Storage": 272.0,
    "Hydro Run-of-river and poundage": 1383.0,
    "Hydro Water Reservoir": 1558.0,
    "Marine": 0.0,
    "Nuclear": 6992.0,
    "Other": 13.0,
    "Other renewable": 108.0,
    "Solar": 127.0,
    "Waste": 263.0,
    "Wind Offshore": 0.0,
    "Wind Onshore": 12535.0
  },
  "1556229600000": {
    "Biomass": 178.0,
    "Fossil Brown coal/Lignite": 0.0,
    "Fossil Coal-derived gas": 0.0,
    "Fossil Gas": 4377.0,
    "Fossil Hard coal": 662.0,
    "Fossil Oil": 244.0,
    "Fossil Oil shale": 0.0,
    "Fossil Peat": 0.0,
    "Geothermal": 0.0,
    "Hydro Pumped Storage": 833.0,
    "Hydro Run-of-river and poundage": 1317.0,
    "Hydro Water Reservoir": 1217.0,
    "Marine": 0.0,
    "Nuclear": 6993.0,
    "Other": 13.0,
    "Other renewable": 107.0,
    "Solar": 73.0,
    "Waste": 260.0,
    "Wind Offshore": 0.0,
    "Wind Onshore": 12543.0
  }
}