{
  "1588118400000": {
    "Fossil Brown coal/Lignite": 437.0,
    "Fossil Gas": 1094.0,
    "Fossil Oil": 0.0,
    "Hydro Pumped Storage": 0.0,
    "Hydro Water Reservoir": 53.0,
    "Solar": 0.0,
    "Wind Onshore": 469.0
  },
  "1588122000000": {
    "Fossil Brown coal/Lignite": 439.0,
    "Fossil Gas": 1027.0,
    "Fossil Oil": 0.0,
    "Hydro Pumped Storage": 0.0,
    "Hydro Water Reservoir": 53.0,
    "Solar": 0.0,
    "Wind Onshore": 496.0
  },
  "1588125600000": {
    "Fossil Brown coal/Lignite": 442.0,
    "Fossil Gas": 950.0,
    "Fossil Oil": 0.0,
    "Hydro Pumped Storage": 0.0,
    "Hydro Water Reservoir": 52.0,
    "Solar": 0.0,
    "Wind Onshore": 637.0
  },
  "1588129200000": {
    "Fossil Brown coal/Lignite": 336.0,
    "Fossil Gas": 1148.0,
    "Fossil Oil": 0.0,
    "Hydro Pumped Storage": 0.0,
    "Hydro Water Reservoir": 54.0,
    "Solar": 6.0,
    "Wind Onshore": 587.0
  },
  "1588132800000": {
    "Fossil Brown coal/Lignite": 293.0,
    "Fossil Gas": 1340.0,
    "Fossil Oil": 0.0,
    "Hydro Pumped Storage": 57.0,
    "Hydro Water Reservoir": 71.0,
    "Solar": 121.0,
    "Wind Onshore": 493.0
  },
  "1588136400000": {
    "Fossil Brown coal/Lignite": 292.0,
    "Fossil Gas": 1502.0,
    "Fossil Oil": 0.0,
    "Hydro Pumped Storage": 362.0,
    "Hydro Water Reservoir": 417.0,
    "Solar": 447.0,
    "Wind Onshore": 387.0
  },
  "1588140000000": {
    "Fossil Brown coal/Lignite": 302.0,
    "Fossil Gas": 1574.0,
    "Fossil Oil": 0.0,
    "Hydro Pumped Storage": 376.0,
    "Hydro Water Reservoir": 453.0,
    "Solar": 838.0,
    "Wind Onshore": 322.0
  }
}