{
  "1528329600000": {
    "Biomass": 4497.0,
    "Fossil Brown coal/Lignite": 16820.0,
    "Fossil Coal-derived gas": 514.0,
    "Fossil Gas": 1638.0,
    "Fossil Hard coal": 6275.0,
    "Fossil Oil": 0.0,
    "Geothermal": 4.0,
    "Hydro Pumped Storage": 258.0,
    "Hydro Run-of-river and poundage": 6133.0,
    "Hydro Water Reservoir": 818.0,
    "Nuclear": 6502.0,
    "Other": 253.0,
    "Other renewable": 148.0,
    "Solar": 0.0,
    "Waste": 492.0,
    "Wind Offshore": 1948.0,
    "Wind Onshore": 11435.0
  },
  "1528330500000": {
    "Biomass": 4509.0,
    "Fossil Brown coal/Lignite": 16805.0,
    "Fossil Coal-derived gas": 518.0,
    "Fossil Gas": 1643.0,
    "Fossil Hard coal": 6274.0,
    "Fossil Oil": 0.0,
    "Geothermal": 4.0,
    "Hydro Pumped Storage": 197.0,
    "Hydro Run-of-river and poundage": 6159.0,
    "Hydro Water Reservoir": 630.0,
    "Nuclear": 6503.0,
    "Other": 253.0,
    "Other renewable": 148.0,
    "Solar": 0.0,
    "Waste": 492.0,
    "Wind Offshore": 1820.0,
    "Wind Onshore": 11271.0
  },
  "1528331400000": {
    "Biomass": 4509.0,
    "Fossil Brown coal/Lignite": 16816.0,
    "Fossil Coal-derived gas": 521.0,
    "Fossil Gas": 1650.0,
    "Fossil Hard coal": 6290.0,
    "Fossil Oil": 0.0,
    "Geothermal": 4.0,
    "Hydro Pumped Storage": 197.0,
    "Hydro Run-of-river and poundage": 6155.0,
    "Hydro Water Reservoir": 563.0,
    "Nuclear": 6507.0,
    "Other": 253.0,
    "Other renewable": 148.0,
    "Solar": 0.0,
    "Waste": 492.0,
    "Wind Offshore": 1714.0,
    "Wind Onshore": 11165.0
  },
  "1528332300000": {
    "Biomass": 4528.0,
    "Fossil Brown coal/Lignite": 16848.0,
    "Fossil Coal-derived gas": 522.0,
    "Fossil Gas": 1648.0,
    "Fossil Hard coal": 6289.0,
    "Fossil Oil": 0.0,
    "Geothermal": 4.0,
    "Hydro Pumped Storage": 200.0,
    "Hydro Run-of-river and poundage": 6152.0,
    "Hydro Water Reservoir": 545.0,
    "Nuclear": 6505.0,
    "Other": 253.0,
    "Other renewable": 148.0,
    "Solar": 0.0,
    "Waste": 492.0,
    "Wind Offshore": 1623.0,
    "Wind Onshore": 11048.0
  },
  "1528333200000": {
    "Biomass": 4530.0,
    "Fossil Brown coal/Lignite": 16807.0,
    "Fossil Coal-derived gas": 522.0,
    "Fossil Gas": 1651.0,
    "Fossil Hard coal": 5982.0,
    "Fossil Oil": 0.0,
    "Geothermal": 4.0,
    "Hydro Pumped Storage": 275.0,
    "Hydro Run-of-river and poundage": 6148.0,
    "Hydro Water Reservoir": 537.0,
    "Nuclear": 6494.0,
    "Other": 253.0,
    "Other renewable": 148.0,
    "Solar": 0.0,
    "Waste": 492.0,
    "Wind Offshore": 1558.0,
    "Wind Onshore": 10951.0
  },
  "1528334100000": {
    "Biomass": 4531.0,
    "Fossil Brown coal/Lignite": 16806.0,
    "Fossil Coal-derived gas": 530.0,
    "Fossil Gas": 1658.0,
    "Fossil Hard coal": 6055.0,
    "Fossil Oil": 0.0,
    "Geothermal": 4.0,
    "Hydro Pumped Storage": 221.0,
    "Hydro Run-of-river and poundage": 6154.0,
    "Hydro Water Reservoir": 524.0,
    "Nuclear": 6480.0,
    "Other": 253.0,
    "Other renewable": 148.0,
    "Solar": 0.0,
    "Waste": 492.0,
    "Wind Offshore": 1533.0,
    "Wind Onshore": 10731.0
  },
  "1528335000000": {
    "Biomass": 4536.0,
    "Fossil Brown coal/Lignite": 16846.0,
    "Fossil Coal-derived gas": 524.0,
    "Fossil Gas": 1660.0,
    "Fossil Hard coal": 6213.0,
    "Fossil Oil": 0.0,
    "Geothermal": 4.0,
    "Hydro Pumped Storage": 195.0,
    "Hydro Run-of-river and poundage": 6169.0,
    "Hydro Water Reservoir": 538.0,
    "Nuclear": 6489.0,
    "Other": 253.0,
    "Other renewable": 148.0,
    "Solar": 0.0,
    "Waste": 492.0,
    "Wind Offshore": 1470.0,
    "Wind Onshore": 10620.0
  },
  "1528335900000": {
    "Biomass": 4525.0,
    "Fossil Brown coal/Lignite": 16815.0,
    "Fossil Coal-derived gas": 517.0,
    "Fossil Gas": 1656.0,
    "Fossil Hard coal": 6283.0,
    "Fossil Oil": 0.0,
    "Geothermal": 4.0,
    "Hydro Pumped Storage": 195.0,
    "Hydro Run-of-river and poundage": 6176.0,
    "Hydro Water Reservoir": 527.0,
    "Nuclear": 6505.0,
    "Other": 253.0,
    "Other renewable": 148.0,
    "Solar": 0.0,
    "Waste": 492.0,
    "Wind Offshore": 1368.0,
    "Wind Onshore": 10514.0
  },
  "1528336800000": {
    "Biomass": 4534.0,
    "Fossil Brown coal/Lignite": 16739.0,
    "Fossil Coal-derived gas": 523.0,
    "Fossil Gas": 1656.0,
    "Fossil Hard coal": 6305.0,
    "Fossil Oil": 0.0,
    "Geothermal": 4.0,
    "Hydro Pumped Storage": 195.0,
    "Hydro Run-of-river and poundage": 6174.0,
    "Hydro Water Reservoir": 498.0,
    "Nuclear": 6505.0,
    "Other": 253.0,
    "Other renewable": 148.0,
    "Solar": 0.0,
    "Waste": 492.0,
    "Wind Offshore": 1301.0,
    "Wind Onshore": 10210.0
  },
  "1528337700000": {
    "Biomass": 4528.0,
    "Fossil Brown coal/Lignite": 16753.0,
    "Fossil Coal-derived gas": 528.0,
    "Fossil Gas": 1687.0,
    "Fossil Hard coal": 6343.0,
    "Fossil Oil": 0.0,
    "Geothermal": 4.0,
    "Hydro Pumped Storage": 195.0,
    "Hydro Run-of-river and poundage": 6163.0,
    "Hydro Water Reservoir": 499.0,
    "Nuclear": 6488.0,
    "Other": 253.0,
    "Other renewable": 148.0,
    "Solar": 0.0,
    "Waste": 492.0,
    "Wind Offshore": 1252.0,
    "Wind Onshore": 10030.0
  },
  "1528338600000": {
    "Biomass": 4539.0,
    "Fossil Brown coal/Lignite": 16833.0,
    "Fossil Coal-derived gas": 520.0,
    "Fossil Gas": 1698.0,
    "Fossil Hard coal": 6436.0,
    "Fossil Oil": 0.0,
    "Geothermal": 4.0,
    "Hydro Pumped Storage": 195.0,
    "Hydro Run-of-river and poundage": 6172.0,
    "Hydro Water Reservoir": 530.0,
    "Nuclear": 6510.0,
    "Other": 253.0,
    "Other renewable": 148.0,
    "Solar": 0.0,
    "Waste": 492.0,
    "Wind Offshore": 1168.0,
    "Wind Onshore": 9668.0
  },
  "1528339500000": {
    "Biomass": 4547.0,
    "Fossil Brown coal/Lignite": 16826.0,
    "Fossil Coal-derived gas": 520.0,
    "Fossil Gas": 1772.0,
    "Fossil Hard coal": 6811.0,
    "Fossil Oil": 0.0,
    "Geothermal": 4.0,
    "Hydro Pumped Storage": 195.0,
    "Hydro Run-of-river and poundage": 6162.0,
    "Hydro Water Reservoir": 532.0,
    "Nuclear": 6508.0,
    "Other": 253.0,
    "Other renewable": 148.0,
    "Solar": 10.0,
    "Waste": 492.0,
    "Wind Offshore": 1066.0,
    "Wind Onshore": 9427.0
  },
  "1528340400000": {
    "Biomass": 4540.0,
    "Fossil Brown coal/Lignite": 16829.0,
    "Fossil Coal-derived gas": 521.0,
    "Fossil Gas": 1846.0,
    "Fossil Hard coal": 7603.0,
    "Fossil Oil": 0.0,
    "Geothermal": 4.0,
    "Hydro Pumped Storage": 241.0,
    "Hydro Run-of-river and poundage": 6146.0,
    "Hydro Water Reservoir": 507.0,
    "Nuclear": 6507.0,
    "Other": 253.0,
    "Other renewable": 148.0,
    "Solar": 64.0,
    "Waste": 492.0,
    "Wind Offshore": 1006.0,
    "Wind Onshore": 9187.0
  },
  "1528341300000": {
    "Biomass": 4558.0,
    "Fossil Brown coal/Lignite": 16827.0,
    "Fossil Coal-derived gas": 517.0,
    "Fossil Gas": 1928.0,
    "Fossil Hard coal": 8464.0,
    "Fossil Oil": 0.0,
    "Geothermal": 4.0,
    "Hydro Pumped Storage": 196.0,
    "Hydro Run-of-river and poundage": 6111.0,
    "Hydro Water Reservoir": 509.0,
    "Nuclear": 6506.0,
    "Other": 253.0,
    "Other renewable": 148.0,
    "Solar": 165.0,
    "Waste": 492.0,
    "Wind Offshore": 961.0,
    "Wind Onshore": 9004.0
  },
  "1528342200000": {
    "Biomass": 4559.0,
    "Fossil Brown coal/Lignite": 16845.0,
    "Fossil Coal-derived gas": 519.0,
    "Fossil Gas": 2153.0,
    "Fossil Hard coal": 9064.0,
    "Fossil Oil": 0.0,
    "Geothermal": 4.0,
    "Hydro Pumped Storage": 213.0,
    "Hydro Run-of-river and poundage": 6090.0,
    "Hydro Water Reservoir": 614.0,
    "Nuclear": 6509.0,
    "Other": 253.0,
    "Other renewable": 148.0,
    "Solar": 386.0,
    "Waste": 492.0,
    "Wind Offshore": 891.0,
    "Wind Onshore": 8653.0
  },
  "1528343100000": {
    "Biomass": 4575.0,
    "Fossil Brown coal/Lignite": 16835.0,
    "Fossil Coal-derived gas": 527.0,
    "Fossil Gas": 2754.0,
    "Fossil Hard coal": 9364.0,
    "Fossil Oil": 0.0,
    "Geothermal": 4.0,
    "Hydro Pumped Storage": 498.0,
    "Hydro Run-of-river and poundage": 6074.0,
    "Hydro Water Reservoir": 697.0,
    "Nuclear": 6514.0,
    "Other": 253.0,
    "Other renewable": 148.0,
    "Solar": 722.0,
    "Waste": 492.0,
    "Wind Offshore": 868.0,
    "Wind Onshore": 8238.0
  },
  "1528344000000": {
    "Biomass": 4582.0,
    "Fossil Brown coal/Lignite": 16753.0,
    "Fossil Coal-derived gas": 528.0,
    "Fossil Gas": 3328.0,
    "Fossil Hard coal": 9975.0,
    "Fossil Oil": 0.0,
    "Geothermal": 4.0,
    "Hydro Pumped Storage": 531.0,
    "Hydro Run-of-river and poundage": 6061.0,
    "Hydro Water Reservoir": 703.0,
    "Nuclear": 6488.0,
    "Other": 253.0,
    "Other renewable": 148.0,
    "Solar": 1156.0,
    "Waste": 492.0,
    "Wind Offshore": 822.0,
    "Wind Onshore": 8100.0
  },
  "1528344900000": {
    "Biomass": 4576.0,
    "Fossil Brown coal/Lignite": 16841.0,
    "Fossil Coal-derived gas": 518.0,
    "Fossil Gas": 3675.0,
    "Fossil Hard coal": 10687.0,
    "Fossil Oil": 0.0,
    "Geothermal": 4.0,
    "Hydro Pumped Storage": 614.0,
    "Hydro Run-of-river and poundage": 6106.0,
    "Hydro Water Reservoir": 742.0,
    "Nuclear": 6491.0,
    "Other": 253.0,
    "Other renewable": 148.0,
    "Solar": 1758.0,
    "Waste": 492.0,
    "Wind Offshore": 766.0,
    "Wind Onshore": 7898.0
  },
  "1528345800000": {
    "Biomass": 4582.0,
    "Fossil Brown coal/Lignite": 16814.0,
    "Fossil Coal-derived gas": 514.0,
    "Fossil Gas": 3566.0,
    "Fossil Hard coal": 11167.0,
    "Fossil Oil": 0.0,
    "Geothermal": 4.0,
    "Hydro Pumped Storage": 1930.0,
    "Hydro Run-of-river and poundage": 6165.0,
    "Hydro Water Reservoir": 1014.0,
    "Nuclear": 6517.0,
    "Other": 253.0,
    "Other renewable": 148.0,
    "Solar": 2440.0,
    "Waste": 492.0,
    "Wind Offshore": 699.0,
    "Wind Onshore": 7488.0
  },
  "1528346700000": {
    "Biomass": 4600.0,
    "Fossil Brown coal/Lignite": 16836.0,
    "Fossil Coal-derived gas": 512.0,
    "Fossil Gas": 3690.0,
    "Fossil Hard coal": 11640.0,
    "Fossil Oil": 0.0,
    "Geothermal": 4.0,
    "Hydro Pumped Storage": 2524.0,
    "Hydro Run-of-river and poundage": 6236.0,
    "Hydro Water Reservoir": 1088.0,
    "Nuclear": 6520.0,
    "Other": 253.0,
    "Other renewable": 148.0,
    "Solar": 3273.0,
    "Waste": 492.0,
    "Wind Offshore": 660.0,
    "Wind Onshore": 6663.0
  },
  "1528347600000": {
    "Biomass": 4603.0,
    "Fossil Brown coal/Lignite": 16796.0,
    "Fossil Coal-derived gas": 515.0,
    "Fossil Gas": 3877.0,
    "Fossil Hard coal": 11888.0,
    "Fossil Oil": 0.0,
    "Geothermal": 4.0,
    "Hydro Pumped Storage": 2445.0,
    "Hydro Run-of-river and poundage": 6402.0,
    "Hydro Water Reservoir": 1208.0,
    "Nuclear": 6512.0,
    "Other": 253.0,
    "Other renewable": 148.0,
    "Solar": 4256.0,
    "Waste": 492.0,
    "Wind Offshore": 662.0,
    "Wind Onshore": 5852.0
  },
  "1528348500000": {
    "Biomass": 4602.0,
    "Fossil Brown coal/Lignite": 16885.0,
    "Fossil Coal-derived gas": 519.0,
    "Fossil Gas": 3959.0,
    "Fossil Hard coal": 12055.0,
    "Fossil Oil": 0.0,
    "Geothermal": 4.0,
    "Hydro Pumped Storage": 2852.0,
    "Hydro Run-of-river and poundage": 6404.0,
    "Hydro Water Reservoir": 1331.0,
    "Nuclear": 6520.0,
    "Other": 253.0,
    "Other renewable": 148.0,
    "Solar": 5314.0,
    "Waste": 492.0,
    "Wind Offshore": 655.0,
    "Wind Onshore": 5009.0
  },
  "1528349400000": {
    "Biomass": 4609.0,
    "Fossil Brown coal/Lignite": 16881.0,
    "Fossil Coal-derived gas": 524.0,
    "Fossil Gas": 4075.0,
    "Fossil Hard coal": 12095.0,
    "Fossil Oil": 0.0,
    "Geothermal": 4.0,
    "Hydro Pumped Storage": 3120.0,
    "Hydro Run-of-river and poundage": 6373.0,
    "Hydro Water Reservoir": 1405.0,
    "Nuclear": 6522.0,
    "Other": 253.0,
    "Other renewable": 148.0,
    "Solar": 6430.0,
    "Waste": 492.0,
    "Wind Offshore": 650.0,
    "Wind Onshore": 4160.0
  },
  "1528350300000": {
    "Biomass": 4605.0,
    "Fossil Brown coal/Lignite": 16851.0,
    "Fossil Coal-derived gas": 527.0,
    "Fossil Gas": 4281.0,
    "Fossil Hard coal": 12217.0,
    "Fossil Oil": 0.0,
    "Geothermal": 4.0,
    "Hydro Pumped Storage": 3188.0,
    "Hydro Run-of-river and poundage": 6339.0,
    "Hydro Water Reservoir": 1535.0,
    "Nuclear": 6522.0,
    "Other": 253.0,
    "Other renewable": 148.0,
    "Solar": 7526.0,
    "Waste": 492.0,
    "Wind Offshore": 647.0,
    "Wind Onshore": 3526.0
  },
  "1528351200000": {
    "Biomass": 4607.0,
    "Fossil Brown coal/Lignite": 16800.0,
    "Fossil Coal-derived gas": 518.0,
    "Fossil Gas": 4324.0,
    "Fossil Hard coal": 12314.0,
    "Fossil Oil": 30.0,
    "Geothermal": 4.0,
    "Hydro Pumped Storage": 4538.0,
    "Hydro Run-of-river and poundage": 6264.0,
    "Hydro Water Reservoir": 1770.0,
    "Nuclear": 6516.0,
    "Other": 253.0,
    "Other renewable": 148.0,
    "Solar": 8814.0,
    "Waste": 492.0,
    "Wind Offshore": 586.0,
    "Wind Onshore": 3061.0
  },
  "1528352100000": {
    "Biomass": 4610.0,
    "Fossil Brown coal/Lignite": 16828.0,
    "Fossil Coal-derived gas": 514.0,
    "Fossil Gas": 4263.0,
    "Fossil Hard coal": 12361.0,
    "Fossil Oil": 30.0,
    "Geothermal": 4.0,
    "Hydro Pumped Storage": 4157.0,
    "Hydro Run-of-river and poundage": 6176.0,
    "Hydro Water Reservoir": 1781.0,
    "Nuclear": 6519.0,
    "Other": 253.0,
    "Other renewable": 148.0,
    "Solar": 10221.0,
    "Waste": 492.0,
    "Wind Offshore": 544.0,
    "Wind Onshore": 2797.0
  },
  "1528353000000": {
    "Biomass": 4599.0,
    "Fossil Brown coal/Lignite": 16821.0,
    "Fossil Coal-derived gas": 520.0,
    "Fossil Gas": 4278.0,
    "Fossil Hard coal": 12392.0,
    "Fossil Oil": 30.0,
    "Geothermal": 4.0,
    "Hydro Pumped Storage": 3784.0,
    "Hydro Run-of-river and poundage": 6181.0,
    "Hydro Water Reservoir": 1693.0,
    "Nuclear": 6510.0,
    "Other": 253.0,
    "Other renewable": 148.0,
    "Solar": 11607.0,
    "Waste": 492.0,
    "Wind Offshore": 585.0,
    "Wind Onshore": 2598.0
  },
  "1528353900000": {
    "Biomass": 4580.0,
    "Fossil Brown coal/Lignite": 16878.0,
    "Fossil Coal-derived gas": 514.0,
    "Fossil Gas": 4349.0,
    "Fossil Hard coal": 12435.0,
    "Fossil Oil": 30.0,
    "Geothermal": 4.0,
    "Hydro Pumped Storage": 3363.0,
    "Hydro Run-of-river and poundage": 6211.0,
    "Hydro Water Reservoir": 1388.0,
    "Nuclear": 6514.0,
    "Other": 253.0,
    "Other renewable": 148.0,
    "Solar": 12997.0,
    "Waste": 492.0,
    "Wind Offshore": 583.0,
    "Wind Onshore": 2533.0
  },
  "1528354800000": {
    "Biomass": 4572.0,
    "Fossil Brown coal/Lignite": 16837.0,
    "Fossil Coal-derived gas": 510.0,
    "Fossil Gas": 4453.0,
    "Fossil Hard coal": 12482.0,
    "Fossil Oil": 30.0,
    "Geothermal": 4.0,
    "Hydro Pumped Storage": 2423.0,
    "Hydro Run-of-river and poundage": 6183.0,
    "Hydro Water Reservoir": 1397.0,
    "Nuclear": 6513.0,
    "Other": 253.0,
    "Other renewable": 148.0,
    "Solar": 14418.0,
    "Waste": 492.0,
    "Wind Offshore": 565.0,
    "Wind Onshore": 2465.0
  },
  "1528355700000": {
    "Biomass": 4568.0,
    "Fossil Brown coal/Lignite": 16781.0,
    "Fossil Coal-derived gas": 518.0,
    "Fossil Gas": 4507.0,
    "Fossil Hard coal": 12475.0,
    "Fossil Oil": 30.0,
    "Geothermal": 4.0,
    "Hydro Pumped Storage": 1635.0,
    "Hydro Run-of-river and poundage": 6165.0,
    "Hydro Water Reservoir": 1224.0,
    "Nuclear": 6511.0,
    "Other": 253.0,
    "Other renewable": 148.0,
    "Solar": 15617.0,
    "Waste": 492.0,
    "Wind Offshore": 603.0,
    "Wind Onshore": 2409.0
  },
  "1528356600000": {
    "Biomass": 4576.0,
    "Fossil Brown coal/Lignite": 16775.0,
    "Fossil Coal-derived gas": 513.0,
    "Fossil Gas": 4415.0,
    "Fossil Hard coal": 12486.0,
    "Fossil Oil": 30.0,
    "Geothermal": 4.0,
    "Hydro Pumped Storage": 1433.0,
    "Hydro Run-of-river and poundage": 6136.0,
    "Hydro Water Reservoir": 1159.0,
    "Nuclear": 6511.0,
    "Other": 253.0,
    "Other renewable": 148.0,
    "Solar": 16925.0,
    "Waste": 492.0,
    "Wind Offshore": 609.0,
    "Wind Onshore": 2465.0
  },
  "1528357500000": {
    "Biomass": 4580.0,
    "Fossil Brown coal/Lignite": 16790.0,
    "Fossil Coal-derived gas": 514.0,
    "Fossil Gas": 4484.0,
    "Fossil Hard coal": 12435.0,
    "Fossil Oil": 30.0,
    "Geothermal": 4.0,
    "Hydro Pumped Storage": 873.0,
    "Hydro Run-of-river and poundage": 6136.0,
    "Hydro Water Reservoir": 1174.0,
    "Nuclear": 6511.0,
    "Other": 253.0,
    "Other renewable": 148.0,
    "Solar": 18004.0,
    "Waste": 492.0,
    "Wind Offshore": 544.0,
    "Wind Onshore": 2597.0
  },
  "1528358400000": {
    "Biomass": 4573.0,
    "Fossil Brown coal/Lignite": 16833.0,
    "Fossil Coal-derived gas": 521.0,
    "Fossil Gas": 4608.0,
    "Fossil Hard coal": 12298.0,
    "Fossil Oil": 30.0,
    "Geothermal": 4.0,
    "Hydro Pumped Storage": 1584.0,
    "Hydro Run-of-river and poundage": 6054.0,
    "Hydro Water Reservoir": 1342.0,
    "Nuclear": 6507.0,
    "Other": 253.0,
    "Other renewable": 148.0,
    "Solar": 18949.0,
    "Waste": 492.0,
    "Wind Offshore": 507.0,
    "Wind Onshore": 2781.0
  },
  "1528359300000": {
    "Biomass": 4571.0,
    "Fossil Brown coal/Lignite": 16829.0,
    "Fossil Coal-derived gas": 519.0,
    "Fossil Gas": 4627.0,
    "Fossil Hard coal": 12221.0,
    "Fossil Oil": 30.0,
    "Geothermal": 4.0,
    "Hydro Pumped Storage": 1461.0,
    "Hydro Run-of-river and poundage": 5897.0,
    "Hydro Water Reservoir": 1208.0,
    "Nuclear": 6503.0,
    "Other": 253.0,
    "Other renewable": 148.0,
    "Solar": 19856.0,
    "Waste": 492.0,
    "Wind Offshore": 474.0,
    "Wind Onshore": 2868.0
  },
  "1528360200000": {
    "Biomass": 4559.0,
    "Fossil Brown coal/Lignite": 16867.0,
    "Fossil Coal-derived gas": 499.0,
    "Fossil Gas": 4648.0,
    "Fossil Hard coal": 12171.0,
    "Fossil Oil": 30.0,
    "Geothermal": 4.0,
    "Hydro Pumped Storage": 1305.0,
    "Hydro Run-of-river and poundage": 5790.0,
    "Hydro Water Reservoir": 1138.0,
    "Nuclear": 6499.0,
    "Other": 253.0,
    "Other renewable": 148.0,
    "Solar": 20803.0,
    "Waste": 492.0,
    "Wind Offshore": 457.0,
    "Wind Onshore": 3086.0
  },
  "1528361100000": {
    "Biomass": 4542.0,
    "Fossil Brown coal/Lignite": 16805.0,
    "Fossil Coal-derived gas": 504.0,
    "Fossil Gas": 4679.0,
    "Fossil Hard coal": 12138.0,
    "Fossil Oil": 30.0,
    "Geothermal": 4.0,
    "Hydro Pumped Storage": 1129.0,
    "Hydro Run-of-river and poundage": 5714.0,
    "Hydro Water Reservoir": 1086.0,
    "Nuclear": 6491.0,
    "Other": 253.0,
    "Other renewable": 148.0,
    "Solar": 21464.0,
    "Waste": 492.0,
    "Wind Offshore": 443.0,
    "Wind Onshore": 3330.0
  },
  "1528362000000": {
    "Biomass": 4553.0,
    "Fossil Brown coal/Lignite": 16718.0,
    "Fossil Coal-derived gas": 516.0,
    "Fossil Gas": 4573.0,
    "Fossil Hard coal": 12173.0,
    "Fossil Oil": 30.0,
    "Geothermal": 4.0,
    "Hydro Pumped Storage": 1936.0,
    "Hydro Run-of-river and poundage": 5638.0,
    "Hydro Water Reservoir": 1093.0,
    "Nuclear": 6490.0,
    "Other": 253.0,
    "Other renewable": 148.0,
    "Solar": 22038.0,
    "Waste": 492.0,
    "Wind Offshore": 485.0,
    "Wind Onshore": 3546.0
  },
  "1528362900000": {
    "Biomass": 4545.0,
    "Fossil Brown coal/Lignite": 16666.0,
    "Fossil Coal-derived gas": 523.0,
    "Fossil Gas": 4629.0,
    "Fossil Hard coal": 12061.0,
    "Fossil Oil": 30.0,
    "Geothermal": 4.0,
    "Hydro Pumped Storage": 1664.0,
    "Hydro Run-of-river and poundage": 5671.0,
    "Hydro Water Reservoir": 1114.0,
    "Nuclear": 6494.0,
    "Other": 253.0,
    "Other renewable": 148.0,
    "Solar": 22623.0,
    "Waste": 492.0,
    "Wind Offshore": 515.0,
    "Wind Onshore": 3695.0
  },
  "1528363800000": {
    "Biomass": 4545.0,
    "Fossil Brown coal/Lignite": 16653.0,
    "Fossil Coal-derived gas": 518.0,
    "Fossil Gas": 4649.0,
    "Fossil Hard coal": 11951.0,
    "Fossil Oil": 30.0,
    "Geothermal": 4.0,
    "Hydro Pumped Storage": 1333.0,
    "Hydro Run-of-river and poundage": 5759.0,
    "Hydro Water Reservoir": 1068.0,
    "Nuclear": 6492.0,
    "Other": 253.0,
    "Other renewable": 148.0,
    "Solar": 23373.0,
    "Waste": 492.0,
    "Wind Offshore": 552.0,
    "Wind Onshore": 3821.0
  },
  "1528364700000": {
    "Biomass": 4534.0,
    "Fossil Brown coal/Lignite": 16684.0,
    "Fossil Coal-derived gas": 516.0,
    "Fossil Gas": 4775.0,
    "Fossil Hard coal": 11783.0,
    "Fossil Oil": 30.0,
    "Geothermal": 4.0,
    "Hydro Pumped Storage": 1041.0,
    "Hydro Run-of-river and poundage": 5802.0,
    "Hydro Water Reservoir": 1024.0,
    "Nuclear": 6483.0,
    "Other": 253.0,
    "Other renewable": 148.0,
    "Solar": 23902.0,
    "Waste": 492.0,
    "Wind Offshore": 529.0,
    "Wind Onshore": 3819.0
  },
  "1528365600000": {
    "Biomass": 4532.0,
    "Fossil Brown coal/Lignite": 16633.0,
    "Fossil Coal-derived gas": 515.0,
    "Fossil Gas": 4833.0,
    "Fossil Hard coal": 11650.0,
    "Fossil Oil": 30.0,
    "Geothermal": 4.0,
    "Hydro Pumped Storage": 1384.0,
    "Hydro Run-of-river and poundage": 5786.0,
    "Hydro Water Reservoir": 1002.0,
    "Nuclear": 6482.0,
    "Other": 253.0,
    "Other renewable": 148.0,
    "Solar": 24352.0,
    "Waste": 492.0,
    "Wind Offshore": 491.0,
    "Wind Onshore": 3811.0
  },
  "1528366500000": {
    "Biomass": 4528.0,
    "Fossil Brown coal/Lignite": 16656.0,
    "Fossil Coal-derived gas": 519.0,
    "Fossil Gas": 4831.0,
    "Fossil Hard coal": 11596.0,
    "Fossil Oil": 30.0,
    "Geothermal": 4.0,
    "Hydro Pumped Storage": 879.0,
    "Hydro Run-of-river and poundage": 5759.0,
    "Hydro Water Reservoir": 952.0,
    "Nuclear": 6478.0,
    "Other": 253.0,
    "Other renewable": 148.0,
    "Solar": 24692.0,
    "Waste": 492.0,
    "Wind Offshore": 498.0,
    "Wind Onshore": 3734.0
  },
  "1528367400000": {
    "Biomass": 4521.0,
    "Fossil Brown coal/Lignite": 16684.0,
    "Fossil Coal-derived gas": 517.0,
    "Fossil Gas": 4793.0,
    "Fossil Hard coal": 11581.0,
    "Fossil Oil": 30.0,
    "Geothermal": 4.0,
    "Hydro Pumped Storage": 746.0,
    "Hydro Run-of-river and poundage": 5747.0,
    "Hydro Water Reservoir": 958.0,
    "Nuclear": 6479.0,
    "Other": 253.0,
    "Other renewable": 148.0,
    "Solar": 24783.0,
    "Waste": 492.0,
    "Wind Offshore": 510.0,
    "Wind Onshore": 3724.0
  },
  "1528368300000": {
    "Biomass": 4518.0,
    "Fossil Brown coal/Lignite": 16709.0,
    "Fossil Coal-derived gas": 515.0,
    "Fossil Gas": 4776.0,
    "Fossil Hard coal": 11480.0,
    "Fossil Oil": 30.0,
    "Geothermal": 4.0,
    "Hydro Pumped Storage": 896.0,
    "Hydro Run-of-river and poundage": 5728.0,
    "Hydro Water Reservoir": 957.0,
    "Nuclear": 6478.0,
    "Other": 253.0,
    "Other renewable": 148.0,
    "Solar": 24881.0,
    "Waste": 492.0,
    "Wind Offshore": 497.0,
    "Wind Onshore": 3574.0
  },
  "1528369200000": {
    "Biomass": 4524.0,
    "Fossil Brown coal/Lignite": 16685.0,
    "Fossil Coal-derived gas": 515.0,
    "Fossil Gas": 4804.0,
    "Fossil Hard coal": 11428.0,
    "Fossil Oil": 30.0,
    "Geothermal": 4.0,
    "Hydro Pumped Storage": 1424.0,
    "Hydro Run-of-river and poundage": 5695.0,
    "Hydro Water Reservoir": 1049.0,
    "Nuclear": 6473.0,
    "Other": 253.0,
    "Other renewable": 148.0,
    "Solar": 24809.0,
    "Waste": 492.0,
    "Wind Offshore": 487.0,
    "Wind Onshore": 3443.0
  },
  "1528370100000": {
    "Biomass": 4512.0,
    "Fossil Brown coal/Lignite": 16654.0,
    "Fossil Coal-derived gas": 516.0,
    "Fossil Gas": 4768.0,
    "Fossil Hard coal": 11421.0,
    "Fossil Oil": 30.0,
    "Geothermal": 4.0,
    "Hydro Pumped Storage": 1461.0,
    "Hydro Run-of-river and poundage": 5707.0,
    "Hydro Water Reservoir": 1103.0,
    "Nuclear": 6475.0,
    "Other": 253.0,
    "Other renewable": 148.0,
    "Solar": 24703.0,
    "Waste": 492.0,
    "Wind Offshore": 483.0,
    "Wind Onshore": 3370.0
  },
  "1528371000000": {
    "Biomass": 4498.0,
    "Fossil Brown coal/Lignite": 16645.0,
    "Fossil Coal-derived gas": 504.0,
    "Fossil Gas": 4734.0,
    "Fossil Hard coal": 11420.0,
    "Fossil Oil": 30.0,
    "Geothermal": 4.0,
    "Hydro Pumped Storage": 1296.0,
    "Hydro Run-of-river and poundage": 5710.0,
    "Hydro Water Reservoir": 1092.0,
    "Nuclear": 6473.0,
    "Other": 253.0,
    "Other renewable": 148.0,
    "Solar": 24353.0,
    "Waste": 492.0,
    "Wind Offshore": 463.0,
    "Wind Onshore": 3241.0
  },
  "1528371900000": {
    "Biomass": 4490.0,
    "Fossil Brown coal/Lignite": 16631.0,
    "Fossil Coal-derived gas": 503.0,
    "Fossil Gas": 4741.0,
    "Fossil Hard coal": 11400.0,
    "Fossil Oil": 30.0,
    "Geothermal": 4.0,
    "Hydro Pumped Storage": 1082.0,
    "Hydro Run-of-river and poundage": 5698.0,
    "Hydro Water Reservoir": 1022.0,
    "Nuclear": 6462.0,
    "Other": 253.0,
    "Other renewable": 148.0,
    "Solar": 24171.0,
    "Waste": 492.0,
    "Wind Offshore": 427.0,
    "Wind Onshore": 3144.0
  },
  "1528372800000": {
    "Biomass": 4482.0,
    "Fossil Brown coal/Lignite": 16623.0,
    "Fossil Coal-derived gas": 510.0,
    "Fossil Gas": 4778.0,
    "Fossil Hard coal": 11475.0,
    "Fossil Oil": 0.0,
    "Geothermal": 4.0,
    "Hydro Pumped Storage": 1181.0,
    "Hydro Run-of-river and poundage": 5735.0,
    "Hydro Water Reservoir": 1026.0,
    "Nuclear": 6464.0,
    "Other": 253.0,
    "Other renewable": 148.0,
    "Solar": 23756.0,
    "Waste": 492.0,
    "Wind Offshore": 414.0,
    "Wind Onshore": 3009.0
  },
  "1528373700000": {
    "Biomass": 4487.0,
    "Fossil Brown coal/Lignite": 16611.0,
    "Fossil Coal-derived gas": 513.0,
    "Fossil Gas": 4762.0,
    "Fossil Hard coal": 11528.0,
    "Fossil Oil": 0.0,
    "Geothermal": 4.0,
    "Hydro Pumped Storage": 1426.0,
    "Hydro Run-of-river and poundage": 5745.0,
    "Hydro Water Reservoir": 1116.0,
    "Nuclear": 6469.0,
    "Other": 253.0,
    "Other renewable": 148.0,
    "Solar": 23271.0,
    "Waste": 492.0,
    "Wind Offshore": 412.0,
    "Wind Onshore": 2913.0
  },
  "1528374600000": {
    "Biomass": 4472.0,
    "Fossil Brown coal/Lignite": 16591.0,
    "Fossil Coal-derived gas": 519.0,
    "Fossil Gas": 4786.0,
    "Fossil Hard coal": 11640.0,
    "Fossil Oil": 0.0,
    "Geothermal": 4.0,
    "Hydro Pumped Storage": 1561.0,
    "Hydro Run-of-river and poundage": 5738.0,
    "Hydro Water Reservoir": 1155.0,
    "Nuclear": 6472.0,
    "Other": 253.0,
    "Other renewable": 148.0,
    "Solar": 22704.0,
    "Waste": 492.0,
    "Wind Offshore": 371.0,
    "Wind Onshore": 2758.0
  },
  "1528375500000": {
    "Biomass": 4479.0,
    "Fossil Brown coal/Lignite": 16538.0,
    "Fossil Coal-derived gas": 519.0,
    "Fossil Gas": 4789.0,
    "Fossil Hard coal": 11803.0,
    "Fossil Oil": 0.0,
    "Geothermal": 4.0,
    "Hydro Pumped Storage": 1606.0,
    "Hydro Run-of-river and poundage": 5714.0,
    "Hydro Water Reservoir": 1193.0,
    "Nuclear": 6472.0,
    "Other": 253.0,
    "Other renewable": 148.0,
    "Solar": 22280.0,
    "Waste": 492.0,
    "Wind Offshore": 326.0,
    "Wind Onshore": 2554.0
  },
  "1528376400000": {
    "Biomass": 4487.0,
    "Fossil Brown coal/Lignite": 16532.0,
    "Fossil Coal-derived gas": 521.0,
    "Fossil Gas": 4778.0,
    "Fossil Hard coal": 11778.0,
    "Fossil Oil": 0.0,
    "Geothermal": 4.0,
    "Hydro Pumped Storage": 1157.0,
    "Hydro Run-of-river and poundage": 5751.0,
    "Hydro Water Reservoir": 1070.0,
    "Nuclear": 6467.0,
    "Other": 253.0,
    "Other renewable": 148.0,
    "Solar": 21480.0,
    "Waste": 492.0,
    "Wind Offshore": 293.0,
    "Wind Onshore": 2448.0
  },
  "1528377300000": {
    "Biomass": 4477.0,
    "Fossil Brown coal/Lignite": 16596.0,
    "Fossil Coal-derived gas": 519.0,
    "Fossil Gas": 4789.0,
    "Fossil Hard coal": 11826.0,
    "Fossil Oil": 0.0,
    "Geothermal": 4.0,
    "Hydro Pumped Storage": 1402.0,
    "Hydro Run-of-river and poundage": 5781.0,
    "Hydro Water Reservoir": 1165.0,
    "Nuclear": 6461.0,
    "Other": 253.0,
    "Other renewable": 148.0,
    "Solar": 20577.0,
    "Waste": 492.0,
    "Wind Offshore": 281.0,
    "Wind Onshore": 2313.0
  },
  "1528378200000": {
    "Biomass": 4471.0,
    "Fossil Brown coal/Lignite": 16556.0,
    "Fossil Coal-derived gas": 519.0,
    "Fossil Gas": 4797.0,
    "Fossil Hard coal": 11845.0,
    "Fossil Oil": 0.0,
    "Geothermal": 4.0,
    "Hydro Pumped Storage": 1827.0,
    "Hydro Run-of-river and poundage": 5828.0,
    "Hydro Water Reservoir": 1304.0,
    "Nuclear": 6459.0,
    "Other": 253.0,
    "Other renewable": 148.0,
    "Solar": 19694.0,
    "Waste": 492.0,
    "Wind Offshore": 272.0,
    "Wind Onshore": 2236.0
  },
  "1528379100000": {
    "Biomass": 4465.0,
    "Fossil Brown coal/Lignite": 16558.0,
    "Fossil Coal-derived gas": 519.0,
    "Fossil Gas": 4829.0,
    "Fossil Hard coal": 12007.0,
    "Fossil Oil": 0.0,
    "Geothermal": 4.0,
    "Hydro Pumped Storage": 1862.0,
    "Hydro Run-of-river and poundage": 5858.0,
    "Hydro Water Reservoir": 1352.0,
    "Nuclear": 6460.0,
    "Other": 253.0,
    "Other renewable": 148.0,
    "Solar": 18835.0,
    "Waste": 492.0,
    "Wind Offshore": 261.0,
    "Wind Onshore": 2104.0
  },
  "1528380000000": {
    "Biomass": 4444.0,
    "Fossil Brown coal/Lignite": 16608.0,
    "Fossil Coal-derived gas": 518.0,
    "Fossil Gas": 4824.0,
    "Fossil Hard coal": 12147.0,
    "Fossil Oil": 0.0,
    "Geothermal": 4.0,
    "Hydro Pumped Storage": 949.0,
    "Hydro Run-of-river and poundage": 5864.0,
    "Hydro Water Reservoir": 1158.0,
    "Nuclear": 6455.0,
    "Other": 253.0,
    "Other renewable": 148.0,
    "Solar": 17655.0,
    "Waste": 492.0,
    "Wind Offshore": 249.0,
    "Wind Onshore": 2006.0
  },
  "1528380900000": {
    "Biomass": 4419.0,
    "Fossil Brown coal/Lignite": 16647.0,
    "Fossil Coal-derived gas": 515.0,
    "Fossil Gas": 4823.0,
    "Fossil Hard coal": 12310.0,
    "Fossil Oil": 0.0,
    "Geothermal": 4.0,
    "Hydro Pumped Storage": 1615.0,
    "Hydro Run-of-river and poundage": 5876.0,
    "Hydro Water Reservoir": 1409.0,
    "Nuclear": 6458.0,
    "Other": 253.0,
    "Other renewable": 148.0,
    "Solar": 16395.0,
    "Waste": 492.0,
    "Wind Offshore": 231.0,
    "Wind Onshore": 2024.0
  },
  "1528381800000": {
    "Biomass": 4407.0,
    "Fossil Brown coal/Lignite": 16626.0,
    "Fossil Coal-derived gas": 514.0,
    "Fossil Gas": 4807.0,
    "Fossil Hard coal": 12431.0,
    "Fossil Oil": 0.0,
    "Geothermal": 4.0,
    "Hydro Pumped Storage": 2322.0,
    "Hydro Run-of-river and poundage": 5871.0,
    "Hydro Water Reservoir": 1581.0,
    "Nuclear": 6460.0,
    "Other": 253.0,
    "Other renewable": 148.0,
    "Solar": 15188.0,
    "Waste": 492.0,
    "Wind Offshore": 225.0,
    "Wind Onshore": 2163.0
  },
  "1528382700000": {
    "Biomass": 4407.0,
    "Fossil Brown coal/Lignite": 16568.0,
    "Fossil Coal-derived gas": 507.0,
    "Fossil Gas": 4822.0,
    "Fossil Hard coal": 12454.0,
    "Fossil Oil": 0.0,
    "Geothermal": 4.0,
    "Hydro Pumped Storage": 3106.0,
    "Hydro Run-of-river and poundage": 5887.0,
    "Hydro Water Reservoir": 1591.0,
    "Nuclear": 6463.0,
    "Other": 253.0,
    "Other renewable": 148.0,
    "Solar": 13992.0,
    "Waste": 492.0,
    "Wind Offshore": 214.0,
    "Wind Onshore": 2167.0
  },
  "1528383600000": {
    "Biomass": 4401.0,
    "Fossil Brown coal/Lignite": 16655.0,
    "Fossil Coal-derived gas": 506.0,
    "Fossil Gas": 4891.0,
    "Fossil Hard coal": 12514.0,
    "Fossil Oil": 0.0,
    "Geothermal": 4.0,
    "Hydro Pumped Storage": 1256.0,
    "Hydro Run-of-river and poundage": 5974.0,
    "Hydro Water Reservoir": 1324.0,
    "Nuclear": 6458.0,
    "Other": 253.0,
    "Other renewable": 148.0,
    "Solar": 12667.0,
    "Waste": 492.0,
    "Wind Offshore": 210.0,
    "Wind Onshore": 2079.0
  },
  "1528384500000": {
    "Biomass": 4389.0,
    "Fossil Brown coal/Lignite": 16672.0,
    "Fossil Coal-derived gas": 509.0,
    "Fossil Gas": 4844.0,
    "Fossil Hard coal": 12549.0,
    "Fossil Oil": 0.0,
    "Geothermal": 4.0,
    "Hydro Pumped Storage": 1657.0,
    "Hydro Run-of-river and poundage": 6019.0,
    "Hydro Water Reservoir": 1576.0,
    "Nuclear": 6458.0,
    "Other": 253.0,
    "Other renewable": 148.0,
    "Solar": 11331.0,
    "Waste": 492.0,
    "Wind Offshore": 214.0,
    "Wind Onshore": 2067.0
  },
  "1528385400000": {
    "Biomass": 4415.0,
    "Fossil Brown coal/Lignite": 16697.0,
    "Fossil Coal-derived gas": 507.0,
    "Fossil Gas": 4757.0,
    "Fossil Hard coal": 12668.0,
    "Fossil Oil": 0.0,
    "Geothermal": 4.0,
    "Hydro Pumped Storage": 2550.0,
    "Hydro Run-of-river and poundage": 6074.0,
    "Hydro Water Reservoir": 1663.0,
    "Nuclear": 6459.0,
    "Other": 253.0,
    "Other renewable": 148.0,
    "Solar": 10188.0,
    "Waste": 492.0,
    "Wind Offshore": 213.0,
    "Wind Onshore": 2134.0
  },
  "1528386300000": {
    "Biomass": 4424.0,
    "Fossil Brown coal/Lignite": 16641.0,
    "Fossil Coal-derived gas": 500.0,
    "Fossil Gas": 4597.0,
    "Fossil Hard coal": 12787.0,
    "Fossil Oil": 0.0,
    "Geothermal": 4.0,
    "Hydro Pumped Storage": 3522.0,
    "Hydro Run-of-river and poundage": 6123.0,
    "Hydro Water Reservoir": 1828.0,
    "Nuclear": 6460.0,
    "Other": 253.0,
    "Other renewable": 148.0,
    "Solar": 8966.0,
    "Waste": 492.0,
    "Wind Offshore": 217.0,
    "Wind Onshore": 2240.0
  },
  "1528387200000": {
    "Biomass": 4415.0,
    "Fossil Brown coal/Lignite": 16647.0,
    "Fossil Coal-derived gas": 503.0,
    "Fossil Gas": 4384.0,
    "Fossil Hard coal": 12937.0,
    "Fossil Oil": 100.0,
    "Geothermal": 4.0,
    "Hydro Pumped Storage": 3575.0,
    "Hydro Run-of-river and poundage": 6133.0,
    "Hydro Water Reservoir": 1734.0,
    "Nuclear": 6464.0,
    "Other": 253.0,
    "Other renewable": 148.0,
    "Solar": 7776.0,
    "Waste": 492.0,
    "Wind Offshore": 208.0,
    "Wind Onshore": 2318.0
  },
  "1528388100000": {
    "Biomass": 4426.0,
    "Fossil Brown coal/Lignite": 16702.0,
    "Fossil Coal-derived gas": 507.0,
    "Fossil Gas": 4201.0,
    "Fossil Hard coal": 13019.0,
    "Fossil Oil": 58.0,
    "Geothermal": 4.0,
    "Hydro Pumped Storage": 3629.0,
    "Hydro Run-of-river and poundage": 6169.0,
    "Hydro Water Reservoir": 1659.0,
    "Nuclear": 6471.0,
    "Other": 253.0,
    "Other renewable": 148.0,
    "Solar": 6678.0,
    "Waste": 492.0,
    "Wind Offshore": 201.0,
    "Wind Onshore": 2420.0
  },
  "1528389000000": {
    "Biomass": 4424.0,
    "Fossil Brown coal/Lignite": 16634.0,
    "Fossil Coal-derived gas": 502.0,
    "Fossil Gas": 4119.0,
    "Fossil Hard coal": 13033.0,
    "Fossil Oil": 0.0,
    "Geothermal": 4.0,
    "Hydro Pumped Storage": 4586.0,
    "Hydro Run-of-river and poundage": 6188.0,
    "Hydro Water Reservoir": 1801.0,
    "Nuclear": 6470.0,
    "Other": 253.0,
    "Other renewable": 148.0,
    "Solar": 5701.0,
    "Waste": 492.0,
    "Wind Offshore": 198.0,
    "Wind Onshore": 2428.0
  },
  "1528389900000": {
    "Biomass": 4416.0,
    "Fossil Brown coal/Lignite": 16595.0,
    "Fossil Coal-derived gas": 494.0,
    "Fossil Gas": 4126.0,
    "Fossil Hard coal": 13065.0,
    "Fossil Oil": 12.0,
    "Geothermal": 4.0,
    "Hydro Pumped Storage": 5429.0,
    "Hydro Run-of-river and poundage": 6207.0,
    "Hydro Water Reservoir": 1916.0,
    "Nuclear": 6469.0,
    "Other": 253.0,
    "Other renewable": 148.0,
    "Solar": 4782.0,
    "Waste": 492.0,
    "Wind Offshore": 199.0,
    "Wind Onshore": 2494.0
  },
  "1528390800000": {
    "Biomass": 4416.0,
    "Fossil Brown coal/Lignite": 16684.0,
    "Fossil Coal-derived gas": 504.0,
    "Fossil Gas": 4321.0,
    "Fossil Hard coal": 13088.0,
    "Fossil Oil": 218.0,
    "Geothermal": 4.0,
    "Hydro Pumped Storage": 6346.0,
    "Hydro Run-of-river and poundage": 6176.0,
    "Hydro Water Reservoir": 1859.0,
    "Nuclear": 6467.0,
    "Other": 253.0,
    "Other renewable": 148.0,
    "Solar": 3885.0,
    "Waste": 492.0,
    "Wind Offshore": 216.0,
    "Wind Onshore": 2597.0
  },
  "1528391700000": {
    "Biomass": 4418.0,
    "Fossil Brown coal/Lignite": 16684.0,
    "Fossil Coal-derived gas": 513.0,
    "Fossil Gas": 4465.0,
    "Fossil Hard coal": 13093.0,
    "Fossil Oil": 224.0,
    "Geothermal": 4.0,
    "Hydro Pumped Storage": 6599.0,
    "Hydro Run-of-river and poundage": 6200.0,
    "Hydro Water Reservoir": 1878.0,
    "Nuclear": 6466.0,
    "Other": 253.0,
    "Other renewable": 148.0,
    "Solar": 3132.0,
    "Waste": 492.0,
    "Wind Offshore": 227.0,
    "Wind Onshore": 2810.0
  },
  "1528392600000": {
    "Biomass": 4414.0,
    "Fossil Brown coal/Lignite": 16707.0,
    "Fossil Coal-derived gas": 505.0,
    "Fossil Gas": 4487.0,
    "Fossil Hard coal": 13125.0,
    "Fossil Oil": 226.0,
    "Geothermal": 4.0,
    "Hydro Pumped Storage": 6524.0,
    "Hydro Run-of-river and poundage": 6216.0,
    "Hydro Water Reservoir": 1800.0,
    "Nuclear": 6473.0,
    "Other": 253.0,
    "Other renewable": 148.0,
    "Solar": 2509.0,
    "Waste": 492.0,
    "Wind Offshore": 236.0,
    "Wind Onshore": 2979.0
  },
  "1528393500000": {
    "Biomass": 4424.0,
    "Fossil Brown coal/Lignite": 16737.0,
    "Fossil Coal-derived gas": 511.0,
    "Fossil Gas": 4472.0,
    "Fossil Hard coal": 13121.0,
    "Fossil Oil": 43.0,
    "Geothermal": 4.0,
    "Hydro Pumped Storage": 5797.0,
    "Hydro Run-of-river and poundage": 6247.0,
    "Hydro Water Reservoir": 1873.0,
    "Nuclear": 6472.0,
    "Other": 253.0,
    "Other renewable": 148.0,
    "Solar": 1916.0,
    "Waste": 492.0,
    "Wind Offshore": 261.0,
    "Wind Onshore": 3186.0
  },
  "1528394400000": {
    "Biomass": 4431.0,
    "Fossil Brown coal/Lignite": 16741.0,
    "Fossil Coal-derived gas": 508.0,
    "Fossil Gas": 4423.0,
    "Fossil Hard coal": 13078.0,
    "Fossil Oil": 1.0,
    "Geothermal": 4.0,
    "Hydro Pumped Storage": 5134.0,
    "Hydro Run-of-river and poundage": 6272.0,
    "Hydro Water Reservoir": 1757.0,
    "Nuclear": 6473.0,
    "Other": 253.0,
    "Other renewable": 148.0,
    "Solar": 1358.0,
    "Waste": 492.0,
    "Wind Offshore": 271.0,
    "Wind Onshore": 3464.0
  },
  "1528395300000": {
    "Biomass": 4443.0,
    "Fossil Brown coal/Lignite": 16731.0,
    "Fossil Coal-derived gas": 504.0,
    "Fossil Gas": 4376.0,
    "Fossil Hard coal": 13001.0,
    "Fossil Oil": 0.0,
    "Geothermal": 4.0,
    "Hydro Pumped Storage": 4771.0,
    "Hydro Run-of-river and poundage": 6297.0,
    "Hydro Water Reservoir": 1725.0,
    "Nuclear": 6470.0,
    "Other": 253.0,
    "Other renewable": 148.0,
    "Solar": 973.0,
    "Waste": 492.0,
    "Wind Offshore": 274.0,
    "Wind Onshore": 3863.0
  },
  "1528396200000": {
    "Biomass": 4449.0,
    "Fossil Brown coal/Lignite": 16762.0,
    "Fossil Coal-derived gas": 514.0,
    "Fossil Gas": 4444.0,
    "Fossil Hard coal": 12984.0,
    "Fossil Oil": 0.0,
    "Geothermal": 4.0,
    "Hydro Pumped Storage": 4053.0,
    "Hydro Run-of-river and poundage": 6308.0,
    "Hydro Water Reservoir": 1599.0,
    "Nuclear": 6475.0,
    "Other": 253.0,
    "Other renewable": 148.0,
    "Solar": 618.0,
    "Waste": 492.0,
    "Wind Offshore": 266.0,
    "Wind Onshore": 4051.0
  },
  "1528397100000": {
    "Biomass": 4446.0,
    "Fossil Brown coal/Lignite": 16754.0,
    "Fossil Coal-derived gas": 517.0,
    "Fossil Gas": 4575.0,
    "Fossil Hard coal": 12991.0,
    "Fossil Oil": 0.0,
    "Geothermal": 4.0,
    "Hydro Pumped Storage": 3416.0,
    "Hydro Run-of-river and poundage": 6318.0,
    "Hydro Water Reservoir": 1418.0,
    "Nuclear": 6480.0,
    "Other": 253.0,
    "Other renewable": 148.0,
    "Solar": 318.0,
    "Waste": 492.0,
    "Wind Offshore": 278.0,
    "Wind Onshore": 4375.0
  },
  "1528398000000": {
    "Biomass": 4448.0,
    "Fossil Brown coal/Lignite": 16795.0,
    "Fossil Coal-derived gas": 502.0,
    "Fossil Gas": 4615.0,
    "Fossil Hard coal": 12994.0,
    "Fossil Oil": 0.0,
    "Geothermal": 4.0,
    "Hydro Pumped Storage": 3340.0,
    "Hydro Run-of-river and poundage": 6264.0,
    "Hydro Water Reservoir": 1695.0,
    "Nuclear": 6480.0,
    "Other": 253.0,
    "Other renewable": 148.0,
    "Solar": 139.0,
    "Waste": 492.0,
    "Wind Offshore": 290.0,
    "Wind Onshore": 4669.0
  },
  "1528398900000": {
    "Biomass": 4455.0,
    "Fossil Brown coal/Lignite": 16786.0,
    "Fossil Coal-derived gas": 503.0,
    "Fossil Gas": 4603.0,
    "Fossil Hard coal": 13017.0,
    "Fossil Oil": 0.0,
    "Geothermal": 4.0,
    "Hydro Pumped Storage": 3003.0,
    "Hydro Run-of-river and poundage": 6209.0,
    "Hydro Water Reservoir": 1660.0,
    "Nuclear": 6485.0,
    "Other": 253.0,
    "Other renewable": 148.0,
    "Solar": 51.0,
    "Waste": 492.0,
    "Wind Offshore": 306.0,
    "Wind Onshore": 5031.0
  },
  "1528399800000": {
    "Biomass": 4458.0,
    "Fossil Brown coal/Lignite": 16765.0,
    "Fossil Coal-derived gas": 506.0,
    "Fossil Gas": 4598.0,
    "Fossil Hard coal": 13019.0,
    "Fossil Oil": 0.0,
    "Geothermal": 4.0,
    "Hydro Pumped Storage": 2361.0,
    "Hydro Run-of-river and poundage": 6166.0,
    "Hydro Water Reservoir": 1536.0,
    "Nuclear": 6478.0,
    "Other": 253.0,
    "Other renewable": 148.0,
    "Solar": 15.0,
    "Waste": 492.0,
    "Wind Offshore": 308.0,
    "Wind Onshore": 5499.0
  },
  "1528400700000": {
    "Biomass": 4439.0,
    "Fossil Brown coal/Lignite": 16726.0,
    "Fossil Coal-derived gas": 500.0,
    "Fossil Gas": 4598.0,
    "Fossil Hard coal": 12986.0,
    "Fossil Oil": 0.0,
    "Geothermal": 4.0,
    "Hydro Pumped Storage": 1910.0,
    "Hydro Run-of-river and poundage": 6121.0,
    "Hydro Water Reservoir": 1415.0,
    "Nuclear": 6480.0,
    "Other": 253.0,
    "Other renewable": 148.0,
    "Solar": 0.0,
    "Waste": 492.0,
    "Wind Offshore": 299.0,
    "Wind Onshore": 5868.0
  },
  "1528401600000": {
    "Biomass": 4447.0,
    "Fossil Brown coal/Lignite": 16777.0,
    "Fossil Coal-derived gas": 500.0,
    "Fossil Gas": 4433.0,
    "Fossil Hard coal": 12977.0,
    "Fossil Oil": 0.0,
    "Geothermal": 4.0,
    "Hydro Pumped Storage": 2567.0,
    "Hydro Run-of-river and poundage": 6112.0,
    "Hydro Water Reservoir": 1548.0,
    "Nuclear": 6484.0,
    "Other": 253.0,
    "Other renewable": 148.0,
    "Solar": 0.0,
    "Waste": 492.0,
    "Wind Offshore": 325.0,
    "Wind Onshore": 6124.0
  },
  "1528402500000": {
    "Biomass": 4484.0,
    "Fossil Brown coal/Lignite": 16771.0,
    "Fossil Coal-derived gas": 503.0,
    "Fossil Gas": 4311.0,
    "Fossil Hard coal": 12914.0,
    "Fossil Oil": 0.0,
    "Geothermal": 4.0,
    "Hydro Pumped Storage": 2082.0,
    "Hydro Run-of-river and poundage": 6127.0,
    "Hydro Water Reservoir": 1548.0,
    "Nuclear": 6482.0,
    "Other": 253.0,
    "Other renewable": 148.0,
    "Solar": 0.0,
    "Waste": 492.0,
    "Wind Offshore": 339.0,
    "Wind Onshore": 6496.0
  },
  "1528403400000": {
    "Biomass": 4527.0,
    "Fossil Brown coal/Lignite": 16772.0,
    "Fossil Coal-derived gas": 520.0,
    "Fossil Gas": 4152.0,
    "Fossil Hard coal": 12783.0,
    "Fossil Oil": 1.0,
    "Geothermal": 4.0,
    "Hydro Pumped Storage": 1894.0,
    "Hydro Run-of-river and poundage": 6153.0,
    "Hydro Water Reservoir": 1340.0,
    "Nuclear": 6478.0,
    "Other": 253.0,
    "Other renewable": 148.0,
    "Solar": 0.0,
    "Waste": 492.0,
    "Wind Offshore": 330.0,
    "Wind Onshore": 6859.0
  },
  "1528404300000": {
    "Biomass": 4532.0,
    "Fossil Brown coal/Lignite": 16709.0,
    "Fossil Coal-derived gas": 522.0,
    "Fossil Gas": 4126.0,
    "Fossil Hard coal": 12469.0,
    "Fossil Oil": 0.0,
    "Geothermal": 4.0,
    "Hydro Pumped Storage": 1712.0,
    "Hydro Run-of-river and poundage": 6154.0,
    "Hydro Water Reservoir": 1050.0,
    "Nuclear": 6469.0,
    "Other": 253.0,
    "Other renewable": 148.0,
    "Solar": 0.0,
    "Waste": 492.0,
    "Wind Offshore": 324.0,
    "Wind Onshore": 7067.0
  },
  "1528405200000": {
    "Biomass": 4542.0,
    "Fossil Brown coal/Lignite": 16756.0,
    "Fossil Coal-derived gas": 524.0,
    "Fossil Gas": 4030.0,
    "Fossil Hard coal": 12226.0,
    "Fossil Oil": 0.0,
    "Geothermal": 4.0,
    "Hydro Pumped Storage": 578.0,
    "Hydro Run-of-river and poundage": 6168.0,
    "Hydro Water Reservoir": 1006.0,
    "Nuclear": 6491.0,
    "Other": 253.0,
    "Other renewable": 148.0,
    "Solar": 0.0,
    "Waste": 492.0,
    "Wind Offshore": 368.0,
    "Wind Onshore": 7265.0
  },
  "1528406100000": {
    "Biomass": 4579.0,
    "Fossil Brown coal/Lignite": 16683.0,
    "Fossil Coal-derived gas": 510.0,
    "Fossil Gas": 3918.0,
    "Fossil Hard coal": 12034.0,
    "Fossil Oil": 1.0,
    "Geothermal": 4.0,
    "Hydro Pumped Storage": 485.0,
    "Hydro Run-of-river and poundage": 6165.0,
    "Hydro Water Reservoir": 934.0,
    "Nuclear": 6489.0,
    "Other": 253.0,
    "Other renewable": 148.0,
    "Solar": 0.0,
    "Waste": 492.0,
    "Wind Offshore": 400.0,
    "Wind Onshore": 7383.0
  },
  "1528407000000": {
    "Biomass": 4693.0,
    "Fossil Brown coal/Lignite": 16765.0,
    "Fossil Coal-derived gas": 512.0,
    "Fossil Gas": 3839.0,
    "Fossil Hard coal": 11748.0,
    "Fossil Oil": 1.0,
    "Geothermal": 4.0,
    "Hydro Pumped Storage": 408.0,
    "Hydro Run-of-river and poundage": 6203.0,
    "Hydro Water Reservoir": 798.0,
    "Nuclear": 6492.0,
    "Other": 253.0,
    "Other renewable": 148.0,
    "Solar": 0.0,
    "Waste": 492.0,
    "Wind Offshore": 413.0,
    "Wind Onshore": 7287.0
  },
  "1528407900000": {
    "Biomass": 4762.0,
    "Fossil Brown coal/Lignite": 16725.0,
    "Fossil Coal-derived gas": 521.0,
    "Fossil Gas": 3824.0,
    "Fossil Hard coal": 11303.0,
    "Fossil Oil": 0.0,
    "Geothermal": 4.0,
    "Hydro Pumped Storage": 409.0,
    "Hydro Run-of-river and poundage": 6140.0,
    "Hydro Water Reservoir": 731.0,
    "Nuclear": 6489.0,
    "Other": 253.0,
    "Other renewable": 148.0,
    "Solar": 0.0,
    "Waste": 492.0,
    "Wind Offshore": 403.0,
    "Wind Onshore": 7268.0
  },
  "1528408800000": {
    "Biomass": 4782.0,
    "Fossil Brown coal/Lignite": 16844.0,
    "Fossil Coal-derived gas": 347.0,
    "Fossil Gas": 3435.0,
    "Fossil Hard coal": 10953.0,
    "Fossil Oil": 0.0,
    "Geothermal": 4.0,
    "Hydro Pumped Storage": 495.0,
    "Hydro Run-of-river and poundage": 6066.0,
    "Hydro Water Reservoir": 793.0,
    "Nuclear": 6497.0,
    "Other": 256.0,
    "Other renewable": 148.0,
    "Solar": 0.0,
    "Waste": 492.0,
    "Wind Offshore": 366.0,
    "Wind Onshore": 7384.0
  },
  "1528409700000": {
    "Biomass": 4784.0,
    "Fossil Brown coal/Lignite": 16774.0,
    "Fossil Coal-derived gas": 521.0,
    "Fossil Gas": 3212.0,
    "Fossil Hard coal": 10729.0,
    "Fossil Oil": 1.0,
    "Geothermal": 4.0,
    "Hydro Pumped Storage": 290.0,
    "Hydro Run-of-river and poundage": 6115.0,
    "Hydro Water Reservoir": 919.0,
    "Nuclear": 6498.0,
    "Other": 256.0,
    "Other renewable": 148.0,
    "Solar": 0.0,
    "Waste": 492.0,
    "Wind Offshore": 326.0,
    "Wind Onshore": 7079.0
  },
  "1528410600000": {
    "Biomass": 4784.0,
    "Fossil Brown coal/Lignite": 16789.0,
    "Fossil Coal-derived gas": 515.0,
    "Fossil Gas": 3071.0,
    "Fossil Hard coal": 10283.0,
    "Fossil Oil": 1.0,
    "Geothermal": 4.0,
    "Hydro Pumped Storage": 252.0,
    "Hydro Run-of-river and poundage": 6110.0,
    "Hydro Water Reservoir": 975.0,
    "Nuclear": 6499.0,
    "Other": 256.0,
    "Other renewable": 148.0,
    "Solar": 0.0,
    "Waste": 492.0,
    "Wind Offshore": 275.0,
    "Wind Onshore": 6741.0
  },
  "1528411500000": {
    "Biomass": 4795.0,
    "Fossil Brown coal/Lignite": 16741.0,
    "Fossil Coal-derived gas": 517.0,
    "Fossil Gas": 3041.0,
    "Fossil Hard coal": 10122.0,
    "Fossil Oil": 1.0,
    "Geothermal": 4.0,
    "Hydro Pumped Storage": 240.0,
    "Hydro Run-of-river and poundage": 6165.0,
    "Hydro Water Reservoir": 786.0,
    "Nuclear": 6500.0,
    "Other": 256.0,
    "Other renewable": 148.0,
    "Solar": 0.0,
    "Waste": 492.0,
    "Wind Offshore": 233.0,
    "Wind Onshore": 6513.0
  }
}