{
  "1527724800000": {
    "Biomass": 10.0,
    "Fossil Brown coal/Lignite": 2500.0,
    "Fossil Gas": 2.0,
    "Hydro Pumped Storage": 0.0,
    "Hydro Run-of-river and poundage": 510.0,
    "Hydro Water Reservoir": 0.0,
    "Other": 20.0
  },
  "1527728400000": {
    "Biomass": 10.0,
    "Fossil Brown coal/Lignite": 2495.0,
    "Fossil Gas": 2.0,
    "Hydro Pumped Storage": 0.0,
    "Hydro Run-of-river and poundage": 685.0,
    "Hydro Water Reservoir": 0.0,
    "Other": 20.0
  },
  "1527732000000": {
    "Biomass": 10.0,
    "Fossil Brown coal/Lignite": 2519.0,
    "Fossil Gas": 2.0,
    "Hydro Pumped Storage": 0.0,
    "Hydro Run-of-river and poundage": 675.0,
    "Hydro Water Reservoir": 0.0,
    "Other": 20.0
  },
  "1527735600000": {
    "Biomass": 10.0,
    "Fossil Brown coal/Lignite": 2508.0,
    "Fossil Gas": 2.0,
    "Hydro Pumped Storage": 0.0,
    "Hydro Run-of-river and poundage": 586.0,
    "Hydro Water Reservoir": 0.0,
    "Other": 20.0
  },
  "1527739200000": {
    "Biomass": 10.0,
    "Fossil Brown coal/Lignite": 2565.0,
    "Fossil Gas": 2.0,
    "Hydro Pumped Storage": 0.0,
    "Hydro Run-of-river and poundage": 651.0,
    "Hydro Water Reservoir": 71.0,
    "Other": 20.0
  },
  "1527742800000": {
    "Biomass": 10.0,
    "Fossil Brown coal/Lignite": 2599.0,
    "Fossil Gas": 2.0,
    "Hydro Pumped Storage": 0.0,
    "Hydro Run-of-river and poundage": 1206.0,
    "Hydro Water Reservoir": 131.0,
    "Other": 20.0
  },
  "1527746400000": {
    "Biomass": 10.0,
    "Fossil Brown coal/Lignite": 2585.0,
    "Fossil Gas": 2.0,
    "Hydro Pumped Storage": 0.0,
    "Hydro Run-of-river and poundage": 1565.0,
    "Hydro Water Reservoir": 131.0,
    "Other": 20.0
  },
  "1527750000000": {
    "Biomass": 10.0,
    "Fossil Brown coal/Lignite": 2608.0,
    "Fossil Gas": 2.0,
    "Hydro Pumped Storage": 0.0,
    "Hydro Run-of-river and poundage": 1542.0,
    "Hydro Water Reservoir": 131.0,
    "Other": 20.0
  },
  "1527753600000": {
    "Biomass": 10.0,
    "Fossil Brown coal/Lignite": 2596.0,
    "Fossil Gas": 2.0,
    "Hydro Pumped Storage": 0.0,
    "Hydro Run-of-river and poundage": 1539.0,
    "Hydro Water Reservoir": 133.0,
    "Other": 20.0
  },
  "1527757200000": {
    "Biomass": 10.0,
    "Fossil Brown coal/Lignite": 2502.0,
    "Fossil Gas": 2.0,
    "Hydro Pumped Storage": 0.0,
    "Hydro Run-of-river and poundage": 1631.0,
    "Hydro Water Reservoir": 134.0,
    "Other": 20.0
  },
  "1527760800000": {
    "Biomass": 10.0,
    "Fossil Brown coal/Lignite": 2423.0,
    "Fossil Gas": 2.0,
    "Hydro Pumped Storage": 102.0,
    "Hydro Run-of-river and poundage": 1635.0,
    "Hydro Water Reservoir": 128.0,
    "Other": 20.0
  },
  "1527764400000": {
    "Biomass": 10.0,
    "Fossil Brown coal/Lignite": 2514.0,
    "Fossil Gas": 2.0,
    "Hydro Pumped Storage": 205.0,
    "Hydro Run-of-river and poundage": 1427.0,
    "Hydro Water Reservoir": 130.0,
    "Other": 20.0
  },
  "1527768000000": {
    "Biomass": 10.0,
    "Fossil Brown coal/Lignite": 2564.0,
    "Fossil Gas": 2.0,
    "Hydro Pumped Storage": 33.0,
    "Hydro Run-of-river and poundage": 1490.0,
    "Hydro Water Reservoir": 166.0,
    "Other": 20.0
  },
  "1527771600000": {
    "Biomass": 10.0,
    "Fossil Brown coal/Lignite": 2616.0,
    "Fossil Gas": 2.0,
    "Hydro Pumped Storage": 0.0,
    "Hydro Run-of-river and poundage": 1424.0,
    "Hydro Water Reservoir": 171.0,
    "Other": 20.0
  },
  "1527775200000": {
    "Biomass": 10.0,
    "Fossil Brown coal/Lignite": 2615.0,
    "Fossil Gas": 2.0,
    "Hydro Pumped Storage": 0.0,
    "Hydro Run-of-river and poundage": 1464.0,
    "Hydro Water Reservoir": 172.0,
    "Other": 20.0
  },
  "1527778800000": {
    "Biomass": 10.0,
    "Fossil Brown coal/Lignite": 2571.0,
    "Fossil Gas": 2.0,
    "Hydro Pumped Storage": 0.0,
    "Hydro Run-of-river and poundage": 1498.0,
    "Hydro Water Reservoir": 156.0,
    "Other": 20.0
  },
  "1527782400000": {
    "Biomass": 10.0,
    "Fossil Brown coal/Lignite": 2437.0,
    "Fossil Gas": 2.0,
    "Hydro Pumped Storage": 151.0,
    "Hydro Run-of-river and poundage": 1556.0,
    "Hydro Water Reservoir": 143.0,
    "Other": 20.0
  },
  "1527786000000": {
    "Biomass": 10.0,
    "Fossil Brown coal/Lignite": 2512.0,
    "Fossil Gas": 2.0,
    "Hydro Pumped Storage": 204.0,
    "Hydro Run-of-river and poundage": 1472.0,
    "Hydro Water Reservoir": 142.0,
    "Other": 20.0
  },
  "1527789600000": {
    "Biomass": 10.0,
    "Fossil Brown coal/Lignite": 2498.0,
    "Fossil Gas": 2.0,
    "Hydro Pumped Storage": 204.0,
    "Hydro Run-of-river and poundage": 1486.0,
    "Hydro Water Reservoir": 141.0,
    "Other": 20.0
  },
  "1527793200000": {
    "Biomass": 10.0,
    "Fossil Brown coal/Lignite": 2442.0,
    "Fossil Gas": 2.0,
    "Hydro Pumped Storage": 204.0,
    "Hydro Run-of-river and poundage": 1598.0,
    "Hydro Water Reservoir": 139.0,
    "Other": 20.0
  },
  "1527796800000": {
    "Biomass": 10.0,
    "Fossil Brown coal/Lignite": 2432.0,
    "Fossil Gas": 2.0,
    "Hydro Pumped Storage": 204.0,
    "Hydro Run-of-river and poundage": 1137.0,
    "Hydro Water Reservoir": 100.0,
    "Other": 20.0
  },
  "1527800400000": {
    "Biomass": 10.0,
    "Fossil Brown coal/Lignite": 2485.0,
    "Fossil Gas": 2.0,
    "Hydro Pumped Storage": 166.0,
    "Hydro Run-of-river and poundage": 844.0,
    "Hydro Water Reservoir": 100.0,
    "Other": 20.0
  },
  "1527804000000": {
    "Biomass": 10.0,
    "Fossil Brown coal/Lignite": 2479.0,
    "Fossil Gas": 2.0,
    "Hydro Pumped Storage": 0.0,
    "Hydro Run-of-river and poundage": 720.0,
    "Hydro Water Reservoir": 101.0,
    "Other": 20.0
  }
}