{
  "1608768000000": {
    "Biomass": 26.0,
    "Fossil Brown coal/Lignite": 2476.0,
    "Fossil Gas": 1.0,
    "Hydro Pumped Storage": 0.0,
    "Hydro Run-of-river and poundage": 322.0,
    "Hydro Water Reservoir": 0.0,
    "Other": 86.0
  },
  "1608771600000": {
    "Biomass": 26.0,
    "Fossil Brown coal/Lignite": 2590.0,
    "Fossil Gas": 1.0,
    "Hydro Pumped Storage": 0.0,
    "Hydro Run-of-river and poundage": 363.0,
    "Hydro Water Reservoir": 0.0,
    "Other": 86.0
  },
  "1608775200000": {
    "Biomass": 26.0,
    "Fossil Brown coal/Lignite": 735.0,
    "Fossil Gas": 1.0,
    "Hydro Pumped Storage": 0.0,
    "Hydro Run-of-river and poundage": 327.0,
    "Hydro Water Reservoir": 0.0,
    "Other": 85.0
  }
}