{
  "1450742400000": {
    "Biomass": 114.0,
    "Fossil Brown coal/Lignite": 794.0,
    "Fossil Gas": 418.0,
    "Fossil Oil": 0.0,
    "Hydro Run-of-river and poundage": 11.0,
    "Hydro Water Reservoir": 13.0,
    "Nuclear": 1924.0,
    "Other": 108.0,
    "Other renewable": 8.0,
    "Waste": 21.0,
    "Wind Onshore": 11.0
  },
  "1450743300000": {
    "Biomass": 114.0,
    "Fossil Brown coal/Lignite": 799.0,
    "Fossil Gas": 385.0,
    "Fossil Oil": 0.0,
    "Hydro Run-of-river and poundage": 11.0,
    "Hydro Water Reservoir": 13.0,
    "Nuclear": 1923.0,
    "Other": 108.0,
    "Other renewable": 8.0,
    "Waste": 23.0,
    "Wind Onshore": 10.0
  },
  "1450744200000": {
    "Biomass": 111.0,
    "Fossil Brown coal/Lignite": 802.0,
    "Fossil Gas": 336.0,
    "Fossil Oil": 0.0,
    "Hydro Run-of-river and poundage": 11.0,
    "Hydro Water Reservoir": 13.0,
    "Nuclear": 1923.0,
    "Other": 108.0,
    "Other renewable": 8.0,
    "Waste": 23.0,
    "Wind Onshore": 7.0
  },
  "1450745100000": {
    "Biomass": 106.0,
    "Fossil Brown coal/Lignite": 806.0,
    "Fossil Gas": 330.0,
    "Fossil Oil": 0.0,
    "Hydro Run-of-river and poundage": 11.0,
    "Hydro Water Reservoir": 13.0,
    "Nuclear": 1923.0,
    "Other": 108.0,
    "Other renewable": 7.0,
    "Waste": 23.0,
    "Wind Onshore": 3.0
  },
  "1450746000000": {
    "Biomass": 100.0,
    "Fossil Brown coal/Lignite": 806.0,
    "Fossil Gas": 373.0,
    "Fossil Oil": 0.0,
    "Hydro Run-of-river and poundage": 11.0,
    "Hydro Water Reservoir": 13.0,
    "Nuclear": 1923.0,
    "Other": 82.0,
    "Other renewable": 6.0,
    "Waste": 22.0,
    "Wind Onshore": 5.0
  },
  "1450746900000": {
    "Biomass": 92.0,
    "Fossil Brown coal/Lignite": 805.0,
    "Fossil Gas": 356.0,
    "Fossil Oil": 0.0,
    "Hydro Run-of-river and poundage": 11.0,
    "Hydro Water Reservoir": 13.0,
    "Nuclear": 1923.0,
    "Other": 82.0,
    "Other renewable": 6.0,
    "Waste": 21.0,
    "Wind Onshore": 7.0
  },
  "1450747800000": {
    "Biomass": 91.0,
    "Fossil Brown coal/Lignite": 808.0,
    "Fossil Gas": 318.0,
    "Fossil Oil": 0.0,
    "Hydro Run-of-river and poundage": 11.0,
    "Hydro Water Reservoir": 13.0,
    "Nuclear": 1925.0,
    "Other": 82.0,
    "Other renewable": 6.0,
    "Waste": 21.0,
    "Wind Onshore": 5.0
  },
  "1450748700000": {
    "Biomass": 89.0,
    "Fossil Brown coal/Lignite": 806.0,
    "Fossil Gas": 305.0,
    "Fossil Oil": 0.0,
    "Hydro Run-of-river and poundage": 11.0,
    "Hydro Water Reservoir": 13.0,
    "Nuclear": 1925.0,
    "Other": 82.0,
    "Other renewable": 6.0,
    "Waste": 21.0,
    "Wind Onshore": 7.0
  },
  "1450749600000": {
    "Biomass": 88.0,
    "Fossil Brown coal/Lignite": 810.0,
    "Fossil Gas": 355.0,
    "Fossil Oil": 0.0,
    "Hydro Run-of-river and poundage": 11.0,
    "Hydro Water Reservoir": 13.0,
    "Nuclear": 1925.0,
    "Other": 82.0,
    "Other renewable": 6.0,
    "Waste": 23.0,
    "Wind Onshore": 9.0
  },
  "1450750500000": {
    "Biomass": 89.0,
    "Fossil Brown coal/Lignite": 813.0,
    "Fossil Gas": 325.0,
    "Fossil Oil": 0.0,
    "Hydro Run-of-river and poundage": 11.0,
    "Hydro Water Reservoir": 13.0,
    "Nuclear": 1926.0,
    "Other": 82.0,
    "Other renewable": 5.0,
    "Waste": 23.0,
    "Wind Onshore": 9.0
  },
  "1450751400000": {
    "Biomass": 89.0,
    "Fossil Brown coal/Lignite": 810.0,
    "Fossil Gas": 306.0,
    "Fossil Oil": 0.0,
    "Hydro Run-of-river and poundage": 11.0,
    "Hydro Water Reservoir": 13.0,
    "Nuclear": 1925.0,
    "Other": 82.0,
    "Other renewable": 6.0,
    "Waste": 22.0,
    "Wind Onshore": 7.0
  },
  "1450752300000": {
    "Biomass": 88.0,
    "Fossil Brown coal/Lignite": 827.0,
    "Fossil Gas": 313.0,
    "Fossil Oil": 1.0,
    "Hydro Run-of-river and poundage": 11.0,
    "Hydro Water Reservoir": 13.0,
    "Nuclear": 1925.0,
    "Other": 82.0,
    "Other renewable": 6.0,
    "Waste": 23.0,
    "Wind Onshore": 2.0
  },
  "1450753200000": {
    "Biomass": 88.0,
    "Fossil Brown coal/Lignite": 840.0,
    "Fossil Gas": 346.0,
    "Fossil Oil": 0.0,
    "Hydro Run-of-river and poundage": 11.0,
    "Hydro Water Reservoir": 13.0,
    "Nuclear": 1925.0,
    "Other": 82.0,
    "Other renewable": 6.0,
    "Waste": 21.0,
    "Wind Onshore": 2.0
  },
  "1450754100000": {
    "Biomass": 91.0,
    "Fossil Brown coal/Lignite": 821.0,
    "Fossil Gas": 370.0,
    "Fossil Oil": 0.0,
    "Hydro Run-of-river and poundage": 11.0,
    "Hydro Water Reservoir": 13.0,
    "Nuclear": 1926.0,
    "Other": 82.0,
    "Other renewable": 5.0,
    "Waste": 22.0,
    "Wind Onshore": 1.0
  },
  "1450755000000": {
    "Biomass": 94.0,
    "Fossil Brown coal/Lignite": 818.0,
    "Fossil Gas": 372.0,
    "Fossil Oil": 0.0,
    "Hydro Run-of-river and poundage": 11.0,
    "Hydro Water Reservoir": 13.0,
    "Nuclear": 1927.0,
    "Other": 82.0,
    "Other renewable": 5.0,
    "Waste": 23.0,
    "Wind Onshore": 0.0
  },
  "1450755900000": {
    "Biomass": 101.0,
    "Fossil Brown coal/Lignite": 815.0,
    "Fossil Gas": 428.0,
    "Fossil Oil": 1.0,
    "Hydro Run-of-river and poundage": 11.0,
    "Hydro Water Reservoir": 13.0,
    "Nuclear": 1927.0,
    "Other": 82.0,
    "Other renewable": 5.0,
    "Waste": 22.0,
    "Wind Onshore": 1.0
  },
  "1450756800000": {
    "Biomass": 103.0,
    "Fossil Brown coal/Lignite": 814.0,
    "Fossil Gas": 448.0,
    "Fossil Oil": 1.0,
    "Hydro Run-of-river and poundage": 11.0,
    "Hydro Water Reservoir": 13.0,
    "Nuclear": 1928.0,
    "Other": 108.0,
    "Other renewable": 6.0,
    "Waste": 22.0,
    "Wind Onshore": 0.0
  },
  "1450757700000": {
    "Biomass": 108.0,
    "Fossil Brown coal/Lignite": 818.0,
    "Fossil Gas": 460.0,
    "Fossil Oil": 1.0,
    "Hydro Run-of-river and poundage": 11.0,
    "Hydro Water Reservoir": 13.0,
    "Nuclear": 1926.0,
    "Other": 108.0,
    "Other renewable": 6.0,
    "Waste": 20.0,
    "Wind Onshore": 2.0
  },
  "1450758600000": {
    "Biomass": 115.0,
    "Fossil Brown coal/Lignite": 816.0,
    "Fossil Gas": 500.0,
    "Fossil Oil": 0.0,
    "Hydro Run-of-river and poundage": 11.0,
    "Hydro Water Reservoir": 13.0,
    "Nuclear": 1925.0,
    "Other": 108.0,
    "Other renewable": 7.0,
    "Waste": 21.0,
    "Wind Onshore": 3.0
  },
  "1450759500000": {
    "Biomass": 115.0,
    "Fossil Brown coal/Lignite": 818.0,
    "Fossil Gas": 613.0,
    "Fossil Oil": 0.0,
    "Hydro Run-of-river and poundage": 11.0,
    "Hydro Water Reservoir": 13.0,
    "Nuclear": 1926.0,
    "Other": 108.0,
    "Other renewable": 8.0,
    "Waste": 21.0,
    "Wind Onshore": 7.0
  },
  "1450760400000": {
    "Biomass": 116.0,
    "Fossil Brown coal/Lignite": 798.0,
    "Fossil Gas": 466.0,
    "Fossil Oil": 0.0,
    "Hydro Run-of-river and poundage": 11.0,
    "Hydro Water Reservoir": 13.0,
    "Nuclear": 1928.0,
    "Other": 108.0,
    "Other renewable": 8.0,
    "Waste": 22.0,
    "Wind Onshore": 8.0
  },
  "1450761300000": {
    "Biomass": 114.0,
    "Fossil Brown coal/Lignite": 801.0,
    "Fossil Gas": 478.0,
    "Fossil Oil": 0.0,
    "Hydro Run-of-river and poundage": 11.0,
    "Hydro Water Reservoir": 13.0,
    "Nuclear": 1926.0,
    "Other": 108.0,
    "Other renewable": 8.0,
    "Waste": 23.0,
    "Wind Onshore": 6.0
  },
  "1450762200000": {
    "Biomass": 115.0,
    "Fossil Brown coal/Lignite": 813.0,
    "Fossil Gas": 589.0,
    "Fossil Oil": 0.0,
    "Hydro Run-of-river and poundage": 11.0,
    "Hydro Water Reservoir": 13.0,
    "Nuclear": 1926.0,
    "Other": 108.0,
    "Other renewable": 8.0,
    "Waste": 22.0,
    "Wind Onshore": 3.0
  },
  "1450763100000": {
    "Biomass": 114.0,
    "Fossil Brown coal/Lignite": 842.0,
    "Fossil Gas": 682.0,
    "Fossil Oil": 0.0,
    "Hydro Run-of-river and poundage": 11.0,
    "Hydro Water Reservoir": 14.0,
    "Nuclear": 1926.0,
    "Other": 108.0,
    "Other renewable": 9.0,
    "Waste": 23.0,
    "Wind Onshore": 9.0
  },
  "1450764000000": {
    "Biomass": 114.0,
    "Fossil Brown coal/Lignite": 817.0,
    "Fossil Gas": 612.0,
    "Fossil Oil": 0.0,
    "Hydro Run-of-river and poundage": 12.0,
    "Hydro Water Reservoir": 14.0,
    "Nuclear": 1925.0,
    "Other": 108.0,
    "Other renewable": 9.0,
    "Waste": 22.0,
    "Wind Onshore": 18.0
  },
  "1450764900000": {
    "Biomass": 115.0,
    "Fossil Brown coal/Lignite": 811.0,
    "Fossil Gas": 602.0,
    "Fossil Oil": 0.0,
    "Hydro Run-of-river and poundage": 13.0,
    "Hydro Water Reservoir": 15.0,
    "Nuclear": 1927.0,
    "Other": 108.0,
    "Other renewable": 8.0,
    "Waste": 22.0,
    "Wind Onshore": 22.0
  },
  "1450765800000": {
    "Biomass": 114.0,
    "Fossil Brown coal/Lignite": 719.0,
    "Fossil Gas": 703.0,
    "Fossil Oil": 0.0,
    "Hydro Run-of-river and poundage": 13.0,
    "Hydro Water Reservoir": 15.0,
    "Nuclear": 1926.0,
    "Other": 108.0,
    "Other renewable": 9.0,
    "Waste": 23.0,
    "Wind Onshore": 14.0
  },
  "1450766700000": {
    "Biomass": 114.0,
    "Fossil Brown coal/Lignite": 619.0,
    "Fossil Gas": 811.0,
    "Fossil Oil": 0.0,
    "Hydro Run-of-river and poundage": 13.0,
    "Hydro Water Reservoir": 15.0,
    "Nuclear": 1926.0,
    "Other": 108.0,
    "Other renewable": 9.0,
    "Waste": 23.0,
    "Wind Onshore": 8.0
  },
  "1450767600000": {
    "Biomass": 114.0,
    "Fossil Brown coal/Lignite": 616.0,
    "Fossil Gas": 946.0,
    "Fossil Oil": 0.0,
    "Hydro Run-of-river and poundage": 13.0,
    "Hydro Water Reservoir": 15.0,
    "Nuclear": 1925.0,
    "Other": 108.0,
    "Other renewable": 9.0,
    "Waste": 23.0,
    "Wind Onshore": 5.0
  },
  "1450768500000": {
    "Biomass": 112.0,
    "Fossil Brown coal/Lignite": 621.0,
    "Fossil Gas": 1022.0,
    "Fossil Oil": 0.0,
    "Hydro Run-of-river and poundage": 13.0,
    "Hydro Water Reservoir": 15.0,
    "Nuclear": 1927.0,
    "Other": 108.0,
    "Other renewable": 9.0,
    "Waste": 24.0,
    "Wind Onshore": 4.0
  },
  "1450769400000": {
    "Biomass": 111.0,
    "Fossil Brown coal/Lignite": 636.0,
    "Fossil Gas": 1089.0,
    "Fossil Oil": 0.0,
    "Hydro Run-of-river and poundage": 13.0,
    "Hydro Water Reservoir": 15.0,
    "Nuclear": 1927.0,
    "Other": 108.0,
    "Other renewable": 9.0,
    "Waste": 23.0,
    "Wind Onshore": 5.0
  },
  "1450770300000": {
    "Biomass": 111.0,
    "Fossil Brown coal/Lignite": 653.0,
    "Fossil Gas": 1111.0,
    "Fossil Oil": 0.0,
    "Hydro Run-of-river and poundage": 13.0,
    "Hydro Water Reservoir": 15.0,
    "Nuclear": 1927.0,
    "Other": 108.0,
    "Other renewable": 9.0,
    "Waste": 22.0,
    "Wind Onshore": 5.0
  },
  "1450771200000": {
    "Biomass": 112.0,
    "Fossil Brown coal/Lignite": 654.0,
    "Fossil Gas": 1075.0,
    "Fossil Oil": 0.0,
    "Hydro Run-of-river and poundage": 13.0,
    "Hydro Water Reservoir": 15.0,
    "Nuclear": 1927.0,
    "Other": 108.0,
    "Other renewable": 9.0,
    "Waste": 23.0,
    "Wind Onshore": 1.0
  },
  "1450772100000": {
    "Biomass": 111.0,
    "Fossil Brown coal/Lignite": 643.0,
    "Fossil Gas": 1017.0,
    "Fossil Oil": 0.0,
    "Hydro Run-of-river and poundage": 12.0,
    "Hydro Water Reservoir": 15.0,
    "Nuclear": 1927.0,
    "Other": 108.0,
    "Other renewable": 9.0,
    "Waste": 23.0,
    "Wind Onshore": 0.0
  },
  "1450773000000": {
    "Biomass": 111.0,
    "Fossil Brown coal/Lignite": 636.0,
    "Fossil Gas": 1044.0,
    "Fossil Oil": 0.0,
    "Hydro Run-of-river and poundage": 12.0,
    "Hydro Water Reservoir": 15.0,
    "Nuclear": 1926.0,
    "Other": 108.0,
    "Other renewable": 9.0,
    "Waste": 24.0,
    "Wind Onshore": 1.0
  },
  "1450773900000": {
    "Biomass": 108.0,
    "Fossil Brown coal/Lignite": 645.0,
    "Fossil Gas": 1061.0,
    "Fossil Oil": 0.0,
    "Hydro Run-of-river and poundage": 12.0,
    "Hydro Water Reservoir": 15.0,
    "Nuclear": 1926.0,
    "Other": 108.0,
    "Other renewable": 9.0,
    "Waste": 22.0,
    "Wind Onshore": 0.0
  },
  "1450774800000": {
    "Biomass": 111.0,
    "Fossil Brown coal/Lignite": 646.0,
    "Fossil Gas": 1031.0,
    "Fossil Oil": 0.0,
    "Hydro Run-of-river and poundage": 12.0,
    "Hydro Water Reservoir": 15.0,
    "Nuclear": 1926.0,
    "Other": 108.0,
    "Other renewable": 10.0,
    "Waste": 23.0,
    "Wind Onshore": 0.0
  },
  "1450775700000": {
    "Biomass": 110.0,
    "Fossil Brown coal/Lignite": 645.0,
    "Fossil Gas": 1038.0,
    "Fossil Oil": 0.0,
    "Hydro Run-of-river and poundage": 12.0,
    "Hydro Water Reservoir": 15.0,
    "Nuclear": 1925.0,
    "Other": 108.0,
    "Other renewable": 10.0,
    "Waste": 24.0,
    "Wind Onshore": 0.0
  },
  "1450776600000": {
    "Biomass": 112.0,
    "Fossil Brown coal/Lignite": 643.0,
    "Fossil Gas": 1013.0,
    "Fossil Oil": 0.0,
    "Hydro Run-of-river and poundage": 12.0,
    "Hydro Water Reservoir": 15.0,
    "Nuclear": 1925.0,
    "Other": 108.0,
    "Other renewable": 10.0,
    "Waste": 25.0,
    "Wind Onshore": 1.0
  },
  "1450777500000": {
    "Biomass": 110.0,
    "Fossil Brown coal/Lignite": 636.0,
    "Fossil Gas": 1055.0,
    "Fossil Oil": 0.0,
    "Hydro Run-of-river and poundage": 12.0,
    "Hydro Water Reservoir": 15.0,
    "Nuclear": 1924.0,
    "Other": 108.0,
    "Other renewable": 10.0,
    "Waste": 24.0,
    "Wind Onshore": 0.0
  },
  "1450778400000": {
    "Biomass": 109.0,
    "Fossil Brown coal/Lignite": 637.0,
    "Fossil Gas": 1014.0,
    "Fossil Oil": 0.0,
    "Hydro Run-of-river and poundage": 12.0,
    "Hydro Water Reservoir": 15.0,
    "Nuclear": 1926.0,
    "Other": 108.0,
    "Other renewable": 10.0,
    "Waste": 24.0,
    "Wind Onshore": 2.0
  },
  "1450779300000": {
    "Biomass": 107.0,
    "Fossil Brown coal/Lignite": 635.0,
    "Fossil Gas": 987.0,
    "Fossil Oil": 0.0,
    "Hydro Run-of-river and poundage": 12.0,
    "Hydro Water Reservoir": 15.0,
    "Nuclear": 1924.0,
    "Other": 108.0,
    "Other renewable": 10.0,
    "Waste": 23.0,
    "Wind Onshore": 2.0
  },
  "1450780200000": {
    "Biomass": 105.0,
    "Fossil Brown coal/Lignite": 637.0,
    "Fossil Gas": 973.0,
    "Fossil Oil": 0.0,
    "Hydro Run-of-river and poundage": 12.0,
    "Hydro Water Reservoir": 15.0,
    "Nuclear": 1925.0,
    "Other": 108.0,
    "Other renewable": 10.0,
    "Waste": 25.0,
    "Wind Onshore": 0.0
  },
  "1450781100000": {
    "Biomass": 105.0,
    "Fossil Brown coal/Lignite": 636.0,
    "Fossil Gas": 975.0,
    "Fossil Oil": 0.0,
    "Hydro Run-of-river and poundage": 12.0,
    "Hydro Water Reservoir": 15.0,
    "Nuclear": 1927.0,
    "Other": 108.0,
    "Other renewable": 11.0,
    "Waste": 22.0,
    "Wind Onshore": 1.0
  },
  "1450782000000": {
    "Biomass": 106.0,
    "Fossil Brown coal/Lignite": 624.0,
    "Fossil Gas": 937.0,
    "Fossil Oil": 0.0,
    "Hydro Run-of-river and poundage": 12.0,
    "Hydro Water Reservoir": 15.0,
    "Nuclear": 1926.0,
    "Other": 107.0,
    "Other renewable": 11.0,
    "Waste": 22.0,
    "Wind Onshore": 1.0
  },
  "1450782900000": {
    "Biomass": 105.0,
    "Fossil Brown coal/Lignite": 620.0,
    "Fossil Gas": 924.0,
    "Fossil Oil": 0.0,
    "Hydro Run-of-river and poundage": 12.0,
    "Hydro Water Reservoir": 15.0,
    "Nuclear": 1926.0,
    "Other": 107.0,
    "Other renewable": 11.0,
    "Waste": 23.0,
    "Wind Onshore": 1.0
  },
  "1450783800000": {
    "Biomass": 104.0,
    "Fossil Brown coal/Lignite": 618.0,
    "Fossil Gas": 931.0,
    "Fossil Oil": 0.0,
    "Hydro Run-of-river and poundage": 12.0,
    "Hydro Water Reservoir": 15.0,
    "Nuclear": 1927.0,
    "Other": 107.0,
    "Other renewable": 11.0,
    "Waste": 25.0,
    "Wind Onshore": 1.0
  },
  "1450784700000": {
    "Biomass": 103.0,
    "Fossil Brown coal/Lignite": 613.0,
    "Fossil Gas": 933.0,
    "Fossil Oil": 1.0,
    "Hydro Run-of-river and poundage": 12.0,
    "Hydro Water Reservoir": 15.0,
    "Nuclear": 1927.0,
    "Other": 107.0,
    "Other renewable": 11.0,
    "Waste": 24.0,
    "Wind Onshore": 0.0
  },
  "1450785600000": {
    "Biomass": 104.0,
    "Fossil Brown coal/Lignite": 607.0,
    "Fossil Gas": 1026.0,
    "Fossil Oil": 0.0,
    "Hydro Run-of-river and poundage": 12.0,
    "Hydro Water Reservoir": 15.0,
    "Nuclear": 1928.0,
    "Other": 107.0,
    "Other renewable": 11.0,
    "Waste": 24.0,
    "Wind Onshore": 2.0
  },
  "1450786500000": {
    "Biomass": 104.0,
    "Fossil Brown coal/Lignite": 615.0,
    "Fossil Gas": 1037.0,
    "Fossil Oil": 0.0,
    "Hydro Run-of-river and poundage": 12.0,
    "Hydro Water Reservoir": 15.0,
    "Nuclear": 1928.0,
    "Other": 107.0,
    "Other renewable": 11.0,
    "Waste": 24.0,
    "Wind Onshore": 3.0
  },
  "1450787400000": {
    "Biomass": 105.0,
    "Fossil Brown coal/Lignite": 613.0,
    "Fossil Gas": 1040.0,
    "Fossil Oil": 1.0,
    "Hydro Run-of-river and poundage": 12.0,
    "Hydro Water Reservoir": 15.0,
    "Nuclear": 1928.0,
    "Other": 107.0,
    "Other renewable": 11.0,
    "Waste": 24.0,
    "Wind Onshore": 2.0
  },
  "1450788300000": {
    "Biomass": 105.0,
    "Fossil Brown coal/Lignite": 624.0,
    "Fossil Gas": 1041.0,
    "Fossil Oil": 1.0,
    "Hydro Run-of-river and poundage": 12.0,
    "Hydro Water Reservoir": 15.0,
    "Nuclear": 1926.0,
    "Other": 107.0,
    "Other renewable": 11.0,
    "Waste": 25.0,
    "Wind Onshore": 3.0
  },
  "1450789200000": {
    "Biomass": 104.0,
    "Fossil Brown coal/Lignite": 625.0,
    "Fossil Gas": 1039.0,
    "Fossil Oil": 1.0,
    "Hydro Run-of-river and poundage": 12.0,
    "Hydro Water Reservoir": 15.0,
    "Nuclear": 1926.0,
    "Other": 107.0,
    "Other renewable": 11.0,
    "Waste": 24.0,
    "Wind Onshore": 2.0
  },
  "1450790100000": {
    "Biomass": 105.0,
    "Fossil Brown coal/Lignite": 622.0,
    "Fossil Gas": 1036.0,
    "Fossil Oil": 0.0,
    "Hydro Run-of-river and poundage": 12.0,
    "Hydro Water Reservoir": 15.0,
    "Nuclear": 1926.0,
    "Other": 107.0,
    "Other renewable": 11.0,
    "Waste": 24.0,
    "Wind Onshore": 2.0
  },
  "1450791000000": {
    "Biomass": 105.0,
    "Fossil Brown coal/Lignite": 626.0,
    "Fossil Gas": 1036.0,
    "Fossil Oil": 0.0,
    "Hydro Run-of-river and poundage": 12.0,
    "Hydro Water Reservoir": 15.0,
    "Nuclear": 1926.0,
    "Other": 107.0,
    "Other renewable": 11.0,
    "Waste": 24.0,
    "Wind Onshore": 5.0
  },
  "1450791900000": {
    "Biomass": 105.0,
    "Fossil Brown coal/Lignite": 622.0,
    "Fossil Gas": 1028.0,
    "Fossil Oil": 0.0,
    "Hydro Run-of-river and poundage": 12.0,
    "Hydro Water Reservoir": 15.0,
    "Nuclear": 1924.0,
    "Other": 107.0,
    "Other renewable": 11.0,
    "Waste": 24.0,
    "Wind Onshore": 3.0
  },
  "1450792800000": {
    "Biomass": 104.0,
    "Fossil Brown coal/Lignite": 619.0,
    "Fossil Gas": 910.0,
    "Fossil Oil": 0.0,
    "Hydro Run-of-river and poundage": 12.0,
    "Hydro Water Reservoir": 15.0,
    "Nuclear": 1925.0,
    "Other": 107.0,
    "Other renewable": 11.0,
    "Waste": 25.0,
    "Wind Onshore": 4.0
  },
  "1450793700000": {
    "Biomass": 104.0,
    "Fossil Brown coal/Lignite": 615.0,
    "Fossil Gas": 896.0,
    "Fossil Oil": 0.0,
    "Hydro Run-of-river and poundage": 12.0,
    "Hydro Water Reservoir": 15.0,
    "Nuclear": 1927.0,
    "Other": 107.0,
    "Other renewable": 11.0,
    "Waste": 25.0,
    "Wind Onshore": 8.0
  },
  "1450794600000": {
    "Biomass": 106.0,
    "Fossil Brown coal/Lignite": 616.0,
    "Fossil Gas": 934.0,
    "Fossil Oil": 0.0,
    "Hydro Run-of-river and poundage": 12.0,
    "Hydro Water Reservoir": 15.0,
    "Nuclear": 1928.0,
    "Other": 107.0,
    "Other renewable": 12.0,
    "Waste": 23.0,
    "Wind Onshore": 15.0
  },
  "1450795500000": {
    "Biomass": 109.0,
    "Fossil Brown coal/Lignite": 621.0,
    "Fossil Gas": 954.0,
    "Fossil Oil": 0.0,
    "Hydro Run-of-river and poundage": 12.0,
    "Hydro Water Reservoir": 15.0,
    "Nuclear": 1925.0,
    "Other": 107.0,
    "Other renewable": 11.0,
    "Waste": 23.0,
    "Wind Onshore": 14.0
  },
  "1450796400000": {
    "Biomass": 110.0,
    "Fossil Brown coal/Lignite": 620.0,
    "Fossil Gas": 807.0,
    "Fossil Oil": 0.0,
    "Hydro Run-of-river and poundage": 12.0,
    "Hydro Water Reservoir": 15.0,
    "Nuclear": 1925.0,
    "Other": 107.0,
    "Other renewable": 11.0,
    "Waste": 23.0,
    "Wind Onshore": 21.0
  },
  "1450797300000": {
    "Biomass": 112.0,
    "Fossil Brown coal/Lignite": 616.0,
    "Fossil Gas": 905.0,
    "Fossil Oil": 0.0,
    "Hydro Run-of-river and poundage": 12.0,
    "Hydro Water Reservoir": 15.0,
    "Nuclear": 1927.0,
    "Other": 107.0,
    "Other renewable": 11.0,
    "Waste": 23.0,
    "Wind Onshore": 33.0
  },
  "1450798200000": {
    "Biomass": 113.0,
    "Fossil Brown coal/Lignite": 607.0,
    "Fossil Gas": 977.0,
    "Fossil Oil": 0.0,
    "Hydro Run-of-river and poundage": 12.0,
    "Hydro Water Reservoir": 15.0,
    "Nuclear": 1928.0,
    "Other": 107.0,
    "Other renewable": 11.0,
    "Waste": 23.0,
    "Wind Onshore": 47.0
  },
  "1450799100000": {
    "Biomass": 112.0,
    "Fossil Brown coal/Lignite": 614.0,
    "Fossil Gas": 992.0,
    "Fossil Oil": 0.0,
    "Hydro Run-of-river and poundage": 12.0,
    "Hydro Water Reservoir": 15.0,
    "Nuclear": 1928.0,
    "Other": 107.0,
    "Other renewable": 11.0,
    "Waste": 24.0,
    "Wind Onshore": 48.0
  },
  "1450800000000": {
    "Biomass": 112.0,
    "Fossil Brown coal/Lignite": 619.0,
    "Fossil Gas": 1013.0,
    "Fossil Oil": 0.0,
    "Hydro Run-of-river and poundage": 12.0,
    "Hydro Water Reservoir": 15.0,
    "Nuclear": 1927.0,
    "Other": 107.0,
    "Other renewable": 10.0,
    "Waste": 23.0,
    "Wind Onshore": 52.0
  },
  "1450800900000": {
    "Biomass": 113.0,
    "Fossil Brown coal/Lignite": 618.0,
    "Fossil Gas": 970.0,
    "Fossil Oil": 0.0,
    "Hydro Run-of-river and poundage": 12.0,
    "Hydro Water Reservoir": 15.0,
    "Nuclear": 1928.0,
    "Other": 107.0,
    "Other renewable": 10.0,
    "Waste": 24.0,
    "Wind Onshore": 62.0
  },
  "1450801800000": {
    "Biomass": 113.0,
    "Fossil Brown coal/Lignite": 620.0,
    "Fossil Gas": 941.0,
    "Fossil Oil": 0.0,
    "Hydro Run-of-river and poundage": 12.0,
    "Hydro Water Reservoir": 15.0,
    "Nuclear": 1928.0,
    "Other": 107.0,
    "Other renewable": 11.0,
    "Waste": 24.0,
    "Wind Onshore": 67.0
  },
  "1450802700000": {
    "Biomass": 113.0,
    "Fossil Brown coal/Lignite": 616.0,
    "Fossil Gas": 915.0,
    "Fossil Oil": 0.0,
    "Hydro Run-of-river and poundage": 12.0,
    "Hydro Water Reservoir": 15.0,
    "Nuclear": 1927.0,
    "Other": 107.0,
    "Other renewable": 11.0,
    "Waste": 25.0,
    "Wind Onshore": 66.0
  },
  "1450803600000": {
    "Biomass": 114.0,
    "Fossil Brown coal/Lignite": 618.0,
    "Fossil Gas": 991.0,
    "Fossil Oil": 0.0,
    "Hydro Run-of-river and poundage": 12.0,
    "Hydro Water Reservoir": 15.0,
    "Nuclear": 1928.0,
    "Other": 109.0,
    "Other renewable": 11.0,
    "Waste": 24.0,
    "Wind Onshore": 55.0
  },
  "1450804500000": {
    "Biomass": 114.0,
    "Fossil Brown coal/Lignite": 617.0,
    "Fossil Gas": 983.0,
    "Fossil Oil": 0.0,
    "Hydro Run-of-river and poundage": 12.0,
    "Hydro Water Reservoir": 15.0,
    "Nuclear": 1929.0,
    "Other": 109.0,
    "Other renewable": 11.0,
    "Waste": 24.0,
    "Wind Onshore": 40.0
  },
  "1450805400000": {
    "Biomass": 113.0,
    "Fossil Brown coal/Lignite": 614.0,
    "Fossil Gas": 981.0,
    "Fossil Oil": 0.0,
    "Hydro Run-of-river and poundage": 12.0,
    "Hydro Water Reservoir": 15.0,
    "Nuclear": 1928.0,
    "Other": 109.0,
    "Other renewable": 11.0,
    "Waste": 24.0,
    "Wind Onshore": 25.0
  },
  "1450806300000": {
    "Biomass": 114.0,
    "Fossil Brown coal/Lignite": 619.0,
    "Fossil Gas": 964.0,
    "Fossil Oil": 0.0,
    "Hydro Run-of-river and poundage": 12.0,
    "Hydro Water Reservoir": 15.0,
    "Nuclear": 1927.0,
    "Other": 109.0,
    "Other renewable": 11.0,
    "Waste": 24.0,
    "Wind Onshore": 29.0
  },
  "1450807200000": {
    "Biomass": 113.0,
    "Fossil Brown coal/Lignite": 623.0,
    "Fossil Gas": 1047.0,
    "Fossil Oil": 0.0,
    "Hydro Run-of-river and poundage": 12.0,
    "Hydro Water Reservoir": 15.0,
    "Nuclear": 1928.0,
    "Other": 110.0,
    "Other renewable": 10.0,
    "Waste": 22.0,
    "Wind Onshore": 23.0
  },
  "1450808100000": {
    "Biomass": 114.0,
    "Fossil Brown coal/Lignite": 622.0,
    "Fossil Gas": 1036.0,
    "Fossil Oil": 0.0,
    "Hydro Run-of-river and poundage": 12.0,
    "Hydro Water Reservoir": 15.0,
    "Nuclear": 1928.0,
    "Other": 110.0,
    "Other renewable": 10.0,
    "Waste": 22.0,
    "Wind Onshore": 17.0
  },
  "1450809000000": {
    "Biomass": 113.0,
    "Fossil Brown coal/Lignite": 617.0,
    "Fossil Gas": 1001.0,
    "Fossil Oil": 0.0,
    "Hydro Run-of-river and poundage": 12.0,
    "Hydro Water Reservoir": 15.0,
    "Nuclear": 1929.0,
    "Other": 110.0,
    "Other renewable": 10.0,
    "Waste": 24.0,
    "Wind Onshore": 12.0
  },
  "1450809900000": {
    "Biomass": 113.0,
    "Fossil Brown coal/Lignite": 608.0,
    "Fossil Gas": 977.0,
    "Fossil Oil": 0.0,
    "Hydro Run-of-river and poundage": 12.0,
    "Hydro Water Reservoir": 15.0,
    "Nuclear": 1930.0,
    "Other": 110.0,
    "Other renewable": 10.0,
    "Waste": 25.0,
    "Wind Onshore": 13.0
  },
  "1450810800000": {
    "Biomass": 114.0,
    "Fossil Brown coal/Lignite": 610.0,
    "Fossil Gas": 1056.0,
    "Fossil Oil": 0.0,
    "Hydro Run-of-river and poundage": 12.0,
    "Hydro Water Reservoir": 15.0,
    "Nuclear": 1929.0,
    "Other": 109.0,
    "Other renewable": 10.0,
    "Waste": 23.0,
    "Wind Onshore": 18.0
  },
  "1450811700000": {
    "Biomass": 114.0,
    "Fossil Brown coal/Lignite": 611.0,
    "Fossil Gas": 1018.0,
    "Fossil Oil": 0.0,
    "Hydro Run-of-river and poundage": 12.0,
    "Hydro Water Reservoir": 15.0,
    "Nuclear": 1928.0,
    "Other": 109.0,
    "Other renewable": 10.0,
    "Waste": 24.0,
    "Wind Onshore": 25.0
  },
  "1450812600000": {
    "Biomass": 114.0,
    "Fossil Brown coal/Lignite": 607.0,
    "Fossil Gas": 1011.0,
    "Fossil Oil": 0.0,
    "Hydro Run-of-river and poundage": 12.0,
    "Hydro Water Reservoir": 15.0,
    "Nuclear": 1928.0,
    "Other": 109.0,
    "Other renewable": 10.0,
    "Waste": 23.0,
    "Wind Onshore": 30.0
  },
  "1450813500000": {
    "Biomass": 113.0,
    "Fossil Brown coal/Lignite": 611.0,
    "Fossil Gas": 968.0,
    "Fossil Oil": 0.0,
    "Hydro Run-of-river and poundage": 12.0,
    "Hydro Water Reservoir": 15.0,
    "Nuclear": 1929.0,
    "Other": 109.0,
    "Other renewable": 9.0,
    "Waste": 23.0,
    "Wind Onshore": 36.0
  },
  "1450814400000": {
    "Biomass": 114.0,
    "Fossil Brown coal/Lignite": 618.0,
    "Fossil Gas": 1051.0,
    "Fossil Oil": 0.0,
    "Hydro Run-of-river and poundage": 12.0,
    "Hydro Water Reservoir": 15.0,
    "Nuclear": 1930.0,
    "Other": 109.0,
    "Other renewable": 9.0,
    "Waste": 23.0,
    "Wind Onshore": 37.0
  },
  "1450815300000": {
    "Biomass": 114.0,
    "Fossil Brown coal/Lignite": 618.0,
    "Fossil Gas": 1032.0,
    "Fossil Oil": 0.0,
    "Hydro Run-of-river and poundage": 12.0,
    "Hydro Water Reservoir": 15.0,
    "Nuclear": 1929.0,
    "Other": 109.0,
    "Other renewable": 10.0,
    "Waste": 23.0,
    "Wind Onshore": 39.0
  },
  "1450816200000": {
    "Biomass": 113.0,
    "Fossil Brown coal/Lignite": 616.0,
    "Fossil Gas": 1022.0,
    "Fossil Oil": 0.0,
    "Hydro Run-of-river and poundage": 12.0,
    "Hydro Water Reservoir": 15.0,
    "Nuclear": 1929.0,
    "Other": 109.0,
    "Other renewable": 10.0,
    "Waste": 22.0,
    "Wind Onshore": 28.0
  },
  "1450817100000": {
    "Biomass": 115.0,
    "Fossil Brown coal/Lignite": 616.0,
    "Fossil Gas": 964.0,
    "Fossil Oil": 0.0,
    "Hydro Run-of-river and poundage": 12.0,
    "Hydro Water Reservoir": 15.0,
    "Nuclear": 1928.0,
    "Other": 109.0,
    "Other renewable": 10.0,
    "Waste": 23.0,
    "Wind Onshore": 20.0
  },
  "1450818000000": {
    "Biomass": 114.0,
    "Fossil Brown coal/Lignite": 611.0,
    "Fossil Gas": 741.0,
    "Fossil Oil": 0.0,
    "Hydro Run-of-river and poundage": 12.0,
    "Hydro Water Reservoir": 14.0,
    "Nuclear": 1928.0,
    "Other": 108.0,
    "Other renewable": 9.0,
    "Waste": 23.0,
    "Wind Onshore": 17.0
  },
  "1450818900000": {
    "Biomass": 114.0,
    "Fossil Brown coal/Lignite": 578.0,
    "Fossil Gas": 696.0,
    "Fossil Oil": 0.0,
    "Hydro Run-of-river and poundage": 12.0,
    "Hydro Water Reservoir": 13.0,
    "Nuclear": 1926.0,
    "Other": 108.0,
    "Other renewable": 9.0,
    "Waste": 23.0,
    "Wind Onshore": 15.0
  },
  "1450819800000": {
    "Biomass": 112.0,
    "Fossil Brown coal/Lignite": 552.0,
    "Fossil Gas": 658.0,
    "Fossil Oil": 0.0,
    "Hydro Run-of-river and poundage": 11.0,
    "Hydro Water Reservoir": 13.0,
    "Nuclear": 1929.0,
    "Other": 108.0,
    "Other renewable": 9.0,
    "Waste": 22.0,
    "Wind Onshore": 15.0
  },
  "1450820700000": {
    "Biomass": 112.0,
    "Fossil Brown coal/Lignite": 565.0,
    "Fossil Gas": 581.0,
    "Fossil Oil": 0.0,
    "Hydro Run-of-river and poundage": 11.0,
    "Hydro Water Reservoir": 13.0,
    "Nuclear": 1928.0,
    "Other": 108.0,
    "Other renewable": 9.0,
    "Waste": 23.0,
    "Wind Onshore": 12.0
  },
  "1450821600000": {
    "Biomass": 112.0,
    "Fossil Brown coal/Lignite": 610.0,
    "Fossil Gas": 659.0,
    "Fossil Oil": 0.0,
    "Hydro Run-of-river and poundage": 11.0,
    "Hydro Water Reservoir": 13.0,
    "Nuclear": 1929.0,
    "Other": 108.0,
    "Other renewable": 9.0,
    "Waste": 22.0,
    "Wind Onshore": 10.0
  },
  "1450822500000": {
    "Biomass": 113.0,
    "Fossil Brown coal/Lignite": 612.0,
    "Fossil Gas": 625.0,
    "Fossil Oil": 0.0,
    "Hydro Run-of-river and poundage": 11.0,
    "Hydro Water Reservoir": 13.0,
    "Nuclear": 1928.0,
    "Other": 108.0,
    "Other renewable": 9.0,
    "Waste": 23.0,
    "Wind Onshore": 9.0
  },
  "1450823400000": {
    "Biomass": 112.0,
    "Fossil Brown coal/Lignite": 610.0,
    "Fossil Gas": 563.0,
    "Fossil Oil": 0.0,
    "Hydro Run-of-river and poundage": 11.0,
    "Hydro Water Reservoir": 13.0,
    "Nuclear": 1927.0,
    "Other": 108.0,
    "Other renewable": 10.0,
    "Waste": 21.0,
    "Wind Onshore": 9.0
  },
  "1450824300000": {
    "Biomass": 112.0,
    "Fossil Brown coal/Lignite": 606.0,
    "Fossil Gas": 516.0,
    "Fossil Oil": 0.0,
    "Hydro Run-of-river and poundage": 11.0,
    "Hydro Water Reservoir": 13.0,
    "Nuclear": 1927.0,
    "Other": 108.0,
    "Other renewable": 9.0,
    "Waste": 23.0,
    "Wind Onshore": 9.0
  }
}